Workbook

Sheet Расчет грейда
L2: Опознавательные цвета
M4: Логичное сочетание
M6: Менее вероятное сочение | R6: А
R7: ИТ
M8: Нелогичное сочетание | R8: КЦ
M10: Невозможное сочетание
BE12: Техническая поддержка, Финдир, Директор по информационным технологиям, Директор по продукту,
J16: 1 | M16: 2 | O16: 3
J17: 1. Данные из паспорта "Знания и умения" | M17: 2. Данные из паспорта "Решение вопросов" | O17: 3. Данные из паспорта "Ответственность" | T17: Если модификатор НЕ меняем на (-) или (+), оставляем ячейку пустой | X17: Технические столбцы для расчета знаний и умений | AA17: Технические столбцы для расчета решения вопросов | AD17: Технические столбцы для расчета ответственности | AG17: Технические столбцы для расчета итоговой формулы | AT17: Технические столбцы для расчета профиля | AV17: 1. Подсчет баллов "Знания и умения" | AW17: 2. Подсчет баллов "Решение вопросов" | AY17: 3. Подсчет баллов "Ответственность" | BA17: Результат показывает, есть ли куда расти относительно вилки баллов | BB17: Профили больше А3 и P4 говорят о сомнительных результатах. Необходимо проверить, является ли такое представление дожности достоверным
A18: Книга | B18: Номер паспорта | C18: Номер Роли | D18: 1 | E18: 2 | F18: 3 | G18: 4 | H18: 5 | I18: Должность | J18: Необходимые умения (10 вопрос) | K18: Умение планировать, организовывать (9 вопрос) | L18: Взаимодействие и коммуникация (8 вопрос) | M18: Область решаемых вопросов (11 вопрос) | N18: Сложность решаемых вопросов (12 вопрос) | O18: Свобода действий должности (16 вопрос) | P18: Величина воздействия (13 вопрос) | Q18: Тип влияния (14 вопрос) | R18: Атрибут | S18: Оклад | T18: Модиф. умения | U18: Модиф. Решение вопросов | V18: Модиф. Свобода д-й | W18: Грейд Sber | X18: Сцепка | Y18: Модификатор | Z18: Цвет | AA18: Модификатор | AB18: Цвет по проценту | AC18: Цвет по баллу | AD18: Сцепка | AE18: Модификатор | AF18: Цвет | AG18: Необходимые умения кратко | AH18: Умение планировать, организовывать кратко | AI18: Взаимодействие и коммуникация кратко | AJ18: Знания и умения балл | AK18: Область решаемых вопросов кратко | AL18: Сложность решаемых вопросов кратко | AM18: Степень владения процессом кратко | AN18: Решение вопросов балл | AO18: Свобода действий | AP18: Величина воздействия | AQ18: Тип влияния | AR18: Баллы ответственность | AS18: Балл итог | AT18: Профиль | AU18: Число шагов | AV18: Модиф. умения | AW18: Модиф. Решение вопросов | AX18: Модиф. Решение вопросов | AY18: Модиф. Свобода д-й | AZ18: ИТОГО | BA18: Баллы относительно медианы | BB18: Тип должности | BC18: Профиль с количеством шагов | BD18: Комментарий к профилю | BE18: Итоговая формула оценки | BF18: Грейд по HAY
W19: =IF(IFERROR(BF19-6,"")<0,0,IFERROR(BF19-6,"")) | X19: =CONCATENATE(K19,L19) | Y19: =CONCATENATE(J19,T19) | Z19: =INDEX('справочная информация'!$U$6:$AK$29,MATCH('Расчет грейда'!$Y19,'справочная информация'!$T$6:$T$29,0),MATCH('Расчет грейда'!$X19,'справочная информация'!$U$5:$AK$5,0)) -> #N/A | AA19: =CONCATENATE(M19,U19) | AB19: =INDEX('справочная информация'!$B$68:$H$83,MATCH('Расчет грейда'!$AA19,'справочная информация'!$A$68:$A$83,0),MATCH('Расчет грейда'!$N19,'справочная информация'!$B$67:$H$67,0)) -> #N/A | AC19: =INDEX('справочная информация'!$D$130:$AD$145,MATCH('Расчет грейда'!$AW19,'справочная информация'!$C$130:$C$145,0),MATCH('Расчет грейда'!$AV19,'справочная информация'!$D$129:$AD$129,0)) -> #N/A | AD19: =CONCATENATE(P19,Q19) | AE19: =CONCATENATE(O19,V19) | AF19: =IFERROR(IF(AND(AD19="",AE19=""),"",INDEX('справочная информация'!$B$188:$Y$211,MATCH('Расчет грейда'!$AE19,'справочная информация'!$A$188:$A$211,0),MATCH('Расчет грейда'!$AD19,'справочная информация'!$B$187:$Y$187,0))),"НЕТ") | AG19: =VLOOKUP(J19,'справочная информация'!$D$267:$E$274,2,0) -> #N/A | AH19: =VLOOKUP(K19,'справочная информация'!$D$279:$E$283,2,0) -> #N/A | AI19: =VLOOKUP(L19,'справочная информация'!$D$288:$E$290,2,0) -> #N/A | AJ19: =AV19 | AK19: =VLOOKUP(M19,'справочная информация'!$D$294:$E$301,2,0) -> #N/A | AL19: =VLOOKUP(N19,'справочная информация'!$D$306:$E$310,2,0) -> #N/A | AM19: =CONCATENATE("(",AW19,")") -> () | AN19: =AX19 | AO19: =VLOOKUP(O19,'справочная информация'!$D$329:$E$336,2,0) -> #N/A | AP19: =VLOOKUP(P19,'справочная информация'!$D$342:$E$349,2,0) -> #N/A | AQ19: =VLOOKUP(Q19,'справочная информация'!$D$316:$E$325,2,0) -> #N/A | AR19: =AY19 | AS19: =AZ19 | AT19: =IF(AND(AX19="",AY19=""),"",IF(AY19>AX19,"A",IF(AX19=AY19,"L","P"))) | AU19: =ABS(MATCH($AX19,'справочная информация'!$A$354:$A$391,0)-MATCH($AY19,'справочная информация'!$A$354:$A$391,0)) -> #N/A | AV19: =IFERROR(INDEX('справочная информация'!$B$6:$R$29,MATCH('Расчет грейда'!$Y19,'справочная информация'!$A$6:$A$29,0),MATCH('Расчет грейда'!$X19,'справочная информация'!$B$5:$R$5,0)),"") | AW19: =IFERROR(INDEX('справочная информация'!$B$37:$H$52,MATCH('Расчет грейда'!$AA19,'справочная информация'!$A$37:$A$52,0),MATCH('Расчет грейда'!$N19,'справочная информация'!$B$36:$H$36,0)),"") | AX19: =IFERROR(INDEX('справочная информация'!$D$108:$AD$123,MATCH('Расчет грейда'!$AW19,'справочная информация'!$C$108:$C$123,0),MATCH('Расчет грейда'!$AV19,'справочная информация'!$D$107:$AD$107,0)),"") | AY19: =IFERROR(INDEX('справочная информация'!$B$158:$Y$181,MATCH('Расчет грейда'!$AE19,'справочная информация'!$A$158:$A$181,0),MATCH('Расчет грейда'!$AD19,'справочная информация'!$B$157:$Y$157,0)),"") | AZ19: =IFERROR(AV19+AX19+AY19,"") | BA19: =IFERROR(CONCATENATE(TEXT(AZ19/INDEX('справочная информация'!$D$223:$D$261,MATCH('Расчет грейда'!$AZ19,'справочная информация'!$C$223:$C$261,1)),"0%")," - процент относительно медианы 100%. ","MIN балл на грейде ",INDEX('справочная информация'!$C$223:$C$261,MATCH('Расчет грейда'!$AZ19,'справочная информация'!$C$223:$C$261,1)),", "," MAX балл на грейде ",INDEX('справочная информация'!$E$223:$E$261,MATCH('Расчет грейда'!$AZ19,'справочная информация'!$C$223:$C$261,1))),"") | BB19: =IFERROR(IF(AND(AX19="",AY19=""),"",IF(AY19>AX19,"Ответственный профиль (ACC)",IF(AY19=AX19,"Профиль равный (L)","Профиль решения вопросов (PS)"))),"") | BC19: =IFERROR(CONCATENATE(AT19,AU19),"") | BD19: =IFERROR(VLOOKUP(BC19,'справочная информация'!$B$416:$C$424,2,0),"Проверить данные, нетипичная должность") -> Проверить данные, нетипичная должность | BE19: =IFERROR(CONCATENATE(AG19,AH19,AI19," ",AJ19," ",AK19,AL19," ",AM19," ",AN19," ",AO19,AP19,AQ19," ",AR19," ",AS19," ",BC19),"") | BF19: =IFERROR(INDEX('справочная информация'!$F$223:$F$261,MATCH('Расчет грейда'!$AZ19,'справочная информация'!$C$223:$C$261,1)),"")
W20: =IF(IFERROR(BF20-6,"")<0,0,IFERROR(BF20-6,"")) | X20: =CONCATENATE(K20,L20) | Y20: =CONCATENATE(J20,T20) | Z20: =INDEX('справочная информация'!$U$6:$AK$29,MATCH('Расчет грейда'!$Y20,'справочная информация'!$T$6:$T$29,0),MATCH('Расчет грейда'!$X20,'справочная информация'!$U$5:$AK$5,0)) -> #N/A | AA20: =CONCATENATE(M20,U20) | AB20: =INDEX('справочная информация'!$B$68:$H$83,MATCH('Расчет грейда'!$AA20,'справочная информация'!$A$68:$A$83,0),MATCH('Расчет грейда'!$N20,'справочная информация'!$B$67:$H$67,0)) -> #N/A | AC20: =INDEX('справочная информация'!$D$130:$AD$145,MATCH('Расчет грейда'!$AW20,'справочная информация'!$C$130:$C$145,0),MATCH('Расчет грейда'!$AV20,'справочная информация'!$D$129:$AD$129,0)) -> #N/A | AD20: =CONCATENATE(P20,Q20) | AE20: =CONCATENATE(O20,V20) | AF20: =IFERROR(IF(AND(AD20="",AE20=""),"",INDEX('справочная информация'!$B$188:$Y$211,MATCH('Расчет грейда'!$AE20,'справочная информация'!$A$188:$A$211,0),MATCH('Расчет грейда'!$AD20,'справочная информация'!$B$187:$Y$187,0))),"НЕТ") | AG20: =VLOOKUP(J20,'справочная информация'!$D$267:$E$274,2,0) -> #N/A | AH20: =VLOOKUP(K20,'справочная информация'!$D$279:$E$283,2,0) -> #N/A | AI20: =VLOOKUP(L20,'справочная информация'!$D$288:$E$290,2,0) -> #N/A | AJ20: =AV20 | AK20: =VLOOKUP(M20,'справочная информация'!$D$294:$E$301,2,0) -> #N/A | AL20: =VLOOKUP(N20,'справочная информация'!$D$306:$E$310,2,0) -> #N/A | AM20: =CONCATENATE("(",AW20,")") -> () | AN20: =AX20 | AO20: =VLOOKUP(O20,'справочная информация'!$D$329:$E$336,2,0) -> #N/A | AP20: =VLOOKUP(P20,'справочная информация'!$D$342:$E$349,2,0) -> #N/A | AQ20: =VLOOKUP(Q20,'справочная информация'!$D$316:$E$325,2,0) -> #N/A | AR20: =AY20 | AS20: =AZ20 | AT20: =IF(AND(AX20="",AY20=""),"",IF(AY20>AX20,"A",IF(AX20=AY20,"L","P"))) | AU20: =ABS(MATCH($AX20,'справочная информация'!$A$354:$A$391,0)-MATCH($AY20,'справочная информация'!$A$354:$A$391,0)) -> #N/A | AV20: =IFERROR(INDEX('справочная информация'!$B$6:$R$29,MATCH('Расчет грейда'!$Y20,'справочная информация'!$A$6:$A$29,0),MATCH('Расчет грейда'!$X20,'справочная информация'!$B$5:$R$5,0)),"") | AW20: =IFERROR(INDEX('справочная информация'!$B$37:$H$52,MATCH('Расчет грейда'!$AA20,'справочная информация'!$A$37:$A$52,0),MATCH('Расчет грейда'!$N20,'справочная информация'!$B$36:$H$36,0)),"") | AX20: =IFERROR(INDEX('справочная информация'!$D$108:$AD$123,MATCH('Расчет грейда'!$AW20,'справочная информация'!$C$108:$C$123,0),MATCH('Расчет грейда'!$AV20,'справочная информация'!$D$107:$AD$107,0)),"") | AY20: =IFERROR(INDEX('справочная информация'!$B$158:$Y$181,MATCH('Расчет грейда'!$AE20,'справочная информация'!$A$158:$A$181,0),MATCH('Расчет грейда'!$AD20,'справочная информация'!$B$157:$Y$157,0)),"") | AZ20: =IFERROR(AV20+AX20+AY20,"") | BA20: =IFERROR(CONCATENATE(TEXT(AZ20/INDEX('справочная информация'!$D$223:$D$261,MATCH('Расчет грейда'!$AZ20,'справочная информация'!$C$223:$C$261,1)),"0%")," - процент относительно медианы 100%. ","MIN балл на грейде ",INDEX('справочная информация'!$C$223:$C$261,MATCH('Расчет грейда'!$AZ20,'справочная информация'!$C$223:$C$261,1)),", "," MAX балл на грейде ",INDEX('справочная информация'!$E$223:$E$261,MATCH('Расчет грейда'!$AZ20,'справочная информация'!$C$223:$C$261,1))),"") | BB20: =IFERROR(IF(AND(AX20="",AY20=""),"",IF(AY20>AX20,"Ответственный профиль (ACC)",IF(AY20=AX20,"Профиль равный (L)","Профиль решения вопросов (PS)"))),"") | BC20: =IFERROR(CONCATENATE(AT20,AU20),"") | BD20: =IFERROR(VLOOKUP(BC20,'справочная информация'!$B$416:$C$424,2,0),"Проверить данные, нетипичная должность") -> Проверить данные, нетипичная должность | BE20: =IFERROR(CONCATENATE(AG20,AH20,AI20," ",AJ20," ",AK20,AL20," ",AM20," ",AN20," ",AO20,AP20,AQ20," ",AR20," ",AS20," ",BC20),"") | BF20: =IFERROR(INDEX('справочная информация'!$F$223:$F$261,MATCH('Расчет грейда'!$AZ20,'справочная информация'!$C$223:$C$261,1)),"")
W21: =IF(IFERROR(BF21-6,"")<0,0,IFERROR(BF21-6,"")) | X21: =CONCATENATE(K21,L21) | Y21: =CONCATENATE(J21,T21) | Z21: =INDEX('справочная информация'!$U$6:$AK$29,MATCH('Расчет грейда'!$Y21,'справочная информация'!$T$6:$T$29,0),MATCH('Расчет грейда'!$X21,'справочная информация'!$U$5:$AK$5,0)) -> #N/A | AA21: =CONCATENATE(M21,U21) | AB21: =INDEX('справочная информация'!$B$68:$H$83,MATCH('Расчет грейда'!$AA21,'справочная информация'!$A$68:$A$83,0),MATCH('Расчет грейда'!$N21,'справочная информация'!$B$67:$H$67,0)) -> #N/A | AC21: =INDEX('справочная информация'!$D$130:$AD$145,MATCH('Расчет грейда'!$AW21,'справочная информация'!$C$130:$C$145,0),MATCH('Расчет грейда'!$AV21,'справочная информация'!$D$129:$AD$129,0)) -> #N/A | AD21: =CONCATENATE(P21,Q21) | AE21: =CONCATENATE(O21,V21) | AF21: =IFERROR(IF(AND(AD21="",AE21=""),"",INDEX('справочная информация'!$B$188:$Y$211,MATCH('Расчет грейда'!$AE21,'справочная информация'!$A$188:$A$211,0),MATCH('Расчет грейда'!$AD21,'справочная информация'!$B$187:$Y$187,0))),"НЕТ") | AG21: =VLOOKUP(J21,'справочная информация'!$D$267:$E$274,2,0) -> #N/A | AH21: =VLOOKUP(K21,'справочная информация'!$D$279:$E$283,2,0) -> #N/A | AI21: =VLOOKUP(L21,'справочная информация'!$D$288:$E$290,2,0) -> #N/A | AJ21: =AV21 | AK21: =VLOOKUP(M21,'справочная информация'!$D$294:$E$301,2,0) -> #N/A | AL21: =VLOOKUP(N21,'справочная информация'!$D$306:$E$310,2,0) -> #N/A | AM21: =CONCATENATE("(",AW21,")") -> () | AN21: =AX21 | AO21: =VLOOKUP(O21,'справочная информация'!$D$329:$E$336,2,0) -> #N/A | AP21: =VLOOKUP(P21,'справочная информация'!$D$342:$E$349,2,0) -> #N/A | AQ21: =VLOOKUP(Q21,'справочная информация'!$D$316:$E$325,2,0) -> #N/A | AR21: =AY21 | AS21: =AZ21 | AT21: =IF(AND(AX21="",AY21=""),"",IF(AY21>AX21,"A",IF(AX21=AY21,"L","P"))) | AU21: =ABS(MATCH($AX21,'справочная информация'!$A$354:$A$391,0)-MATCH($AY21,'справочная информация'!$A$354:$A$391,0)) -> #N/A | AV21: =IFERROR(INDEX('справочная информация'!$B$6:$R$29,MATCH('Расчет грейда'!$Y21,'справочная информация'!$A$6:$A$29,0),MATCH('Расчет грейда'!$X21,'справочная информация'!$B$5:$R$5,0)),"") | AW21: =IFERROR(INDEX('справочная информация'!$B$37:$H$52,MATCH('Расчет грейда'!$AA21,'справочная информация'!$A$37:$A$52,0),MATCH('Расчет грейда'!$N21,'справочная информация'!$B$36:$H$36,0)),"") | AX21: =IFERROR(INDEX('справочная информация'!$D$108:$AD$123,MATCH('Расчет грейда'!$AW21,'справочная информация'!$C$108:$C$123,0),MATCH('Расчет грейда'!$AV21,'справочная информация'!$D$107:$AD$107,0)),"") | AY21: =IFERROR(INDEX('справочная информация'!$B$158:$Y$181,MATCH('Расчет грейда'!$AE21,'справочная информация'!$A$158:$A$181,0),MATCH('Расчет грейда'!$AD21,'справочная информация'!$B$157:$Y$157,0)),"") | AZ21: =IFERROR(AV21+AX21+AY21,"") | BA21: =IFERROR(CONCATENATE(TEXT(AZ21/INDEX('справочная информация'!$D$223:$D$261,MATCH('Расчет грейда'!$AZ21,'справочная информация'!$C$223:$C$261,1)),"0%")," - процент относительно медианы 100%. ","MIN балл на грейде ",INDEX('справочная информация'!$C$223:$C$261,MATCH('Расчет грейда'!$AZ21,'справочная информация'!$C$223:$C$261,1)),", "," MAX балл на грейде ",INDEX('справочная информация'!$E$223:$E$261,MATCH('Расчет грейда'!$AZ21,'справочная информация'!$C$223:$C$261,1))),"") | BB21: =IFERROR(IF(AND(AX21="",AY21=""),"",IF(AY21>AX21,"Ответственный профиль (ACC)",IF(AY21=AX21,"Профиль равный (L)","Профиль решения вопросов (PS)"))),"") | BC21: =IFERROR(CONCATENATE(AT21,AU21),"") | BD21: =IFERROR(VLOOKUP(BC21,'справочная информация'!$B$416:$C$424,2,0),"Проверить данные, нетипичная должность") -> Проверить данные, нетипичная должность | BE21: =IFERROR(CONCATENATE(AG21,AH21,AI21," ",AJ21," ",AK21,AL21," ",AM21," ",AN21," ",AO21,AP21,AQ21," ",AR21," ",AS21," ",BC21),"") | BF21: =IFERROR(INDEX('справочная информация'!$F$223:$F$261,MATCH('Расчет грейда'!$AZ21,'справочная информация'!$C$223:$C$261,1)),"")
W22: =IF(IFERROR(BF22-6,"")<0,0,IFERROR(BF22-6,"")) | X22: =CONCATENATE(K22,L22) | Y22: =CONCATENATE(J22,T22) | Z22: =INDEX('справочная информация'!$U$6:$AK$29,MATCH('Расчет грейда'!$Y22,'справочная информация'!$T$6:$T$29,0),MATCH('Расчет грейда'!$X22,'справочная информация'!$U$5:$AK$5,0)) -> #N/A | AA22: =CONCATENATE(M22,U22) | AB22: =INDEX('справочная информация'!$B$68:$H$83,MATCH('Расчет грейда'!$AA22,'справочная информация'!$A$68:$A$83,0),MATCH('Расчет грейда'!$N22,'справочная информация'!$B$67:$H$67,0)) -> #N/A | AC22: =INDEX('справочная информация'!$D$130:$AD$145,MATCH('Расчет грейда'!$AW22,'справочная информация'!$C$130:$C$145,0),MATCH('Расчет грейда'!$AV22,'справочная информация'!$D$129:$AD$129,0)) -> #N/A | AD22: =CONCATENATE(P22,Q22) | AE22: =CONCATENATE(O22,V22) | AF22: =IFERROR(IF(AND(AD22="",AE22=""),"",INDEX('справочная информация'!$B$188:$Y$211,MATCH('Расчет грейда'!$AE22,'справочная информация'!$A$188:$A$211,0),MATCH('Расчет грейда'!$AD22,'справочная информация'!$B$187:$Y$187,0))),"НЕТ") | AG22: =VLOOKUP(J22,'справочная информация'!$D$267:$E$274,2,0) -> #N/A | AH22: =VLOOKUP(K22,'справочная информация'!$D$279:$E$283,2,0) -> #N/A | AI22: =VLOOKUP(L22,'справочная информация'!$D$288:$E$290,2,0) -> #N/A | AJ22: =AV22 | AK22: =VLOOKUP(M22,'справочная информация'!$D$294:$E$301,2,0) -> #N/A | AL22: =VLOOKUP(N22,'справочная информация'!$D$306:$E$310,2,0) -> #N/A | AM22: =CONCATENATE("(",AW22,")") -> () | AN22: =AX22 | AO22: =VLOOKUP(O22,'справочная информация'!$D$329:$E$336,2,0) -> #N/A | AP22: =VLOOKUP(P22,'справочная информация'!$D$342:$E$349,2,0) -> #N/A | AQ22: =VLOOKUP(Q22,'справочная информация'!$D$316:$E$325,2,0) -> #N/A | AR22: =AY22 | AS22: =AZ22 | AT22: =IF(AND(AX22="",AY22=""),"",IF(AY22>AX22,"A",IF(AX22=AY22,"L","P"))) | AU22: =ABS(MATCH($AX22,'справочная информация'!$A$354:$A$391,0)-MATCH($AY22,'справочная информация'!$A$354:$A$391,0)) -> #N/A | AV22: =IFERROR(INDEX('справочная информация'!$B$6:$R$29,MATCH('Расчет грейда'!$Y22,'справочная информация'!$A$6:$A$29,0),MATCH('Расчет грейда'!$X22,'справочная информация'!$B$5:$R$5,0)),"") | AW22: =IFERROR(INDEX('справочная информация'!$B$37:$H$52,MATCH('Расчет грейда'!$AA22,'справочная информация'!$A$37:$A$52,0),MATCH('Расчет грейда'!$N22,'справочная информация'!$B$36:$H$36,0)),"") | AX22: =IFERROR(INDEX('справочная информация'!$D$108:$AD$123,MATCH('Расчет грейда'!$AW22,'справочная информация'!$C$108:$C$123,0),MATCH('Расчет грейда'!$AV22,'справочная информация'!$D$107:$AD$107,0)),"") | AY22: =IFERROR(INDEX('справочная информация'!$B$158:$Y$181,MATCH('Расчет грейда'!$AE22,'справочная информация'!$A$158:$A$181,0),MATCH('Расчет грейда'!$AD22,'справочная информация'!$B$157:$Y$157,0)),"") | AZ22: =IFERROR(AV22+AX22+AY22,"") | BA22: =IFERROR(CONCATENATE(TEXT(AZ22/INDEX('справочная информация'!$D$223:$D$261,MATCH('Расчет грейда'!$AZ22,'справочная информация'!$C$223:$C$261,1)),"0%")," - процент относительно медианы 100%. ","MIN балл на грейде ",INDEX('справочная информация'!$C$223:$C$261,MATCH('Расчет грейда'!$AZ22,'справочная информация'!$C$223:$C$261,1)),", "," MAX балл на грейде ",INDEX('справочная информация'!$E$223:$E$261,MATCH('Расчет грейда'!$AZ22,'справочная информация'!$C$223:$C$261,1))),"") | BB22: =IFERROR(IF(AND(AX22="",AY22=""),"",IF(AY22>AX22,"Ответственный профиль (ACC)",IF(AY22=AX22,"Профиль равный (L)","Профиль решения вопросов (PS)"))),"") | BC22: =IFERROR(CONCATENATE(AT22,AU22),"") | BD22: =IFERROR(VLOOKUP(BC22,'справочная информация'!$B$416:$C$424,2,0),"Проверить данные, нетипичная должность") -> Проверить данные, нетипичная должность | BE22: =IFERROR(CONCATENATE(AG22,AH22,AI22," ",AJ22," ",AK22,AL22," ",AM22," ",AN22," ",AO22,AP22,AQ22," ",AR22," ",AS22," ",BC22),"") | BF22: =IFERROR(INDEX('справочная информация'!$F$223:$F$261,MATCH('Расчет грейда'!$AZ22,'справочная информация'!$C$223:$C$261,1)),"")
W23: =IF(IFERROR(BF23-6,"")<0,0,IFERROR(BF23-6,"")) | X23: =CONCATENATE(K23,L23) | Y23: =CONCATENATE(J23,T23) | Z23: =INDEX('справочная информация'!$U$6:$AK$29,MATCH('Расчет грейда'!$Y23,'справочная информация'!$T$6:$T$29,0),MATCH('Расчет грейда'!$X23,'справочная информация'!$U$5:$AK$5,0)) -> #N/A | AA23: =CONCATENATE(M23,U23) | AB23: =INDEX('справочная информация'!$B$68:$H$83,MATCH('Расчет грейда'!$AA23,'справочная информация'!$A$68:$A$83,0),MATCH('Расчет грейда'!$N23,'справочная информация'!$B$67:$H$67,0)) -> #N/A | AC23: =INDEX('справочная информация'!$D$130:$AD$145,MATCH('Расчет грейда'!$AW23,'справочная информация'!$C$130:$C$145,0),MATCH('Расчет грейда'!$AV23,'справочная информация'!$D$129:$AD$129,0)) -> #N/A | AD23: =CONCATENATE(P23,Q23) | AE23: =CONCATENATE(O23,V23) | AF23: =IFERROR(IF(AND(AD23="",AE23=""),"",INDEX('справочная информация'!$B$188:$Y$211,MATCH('Расчет грейда'!$AE23,'справочная информация'!$A$188:$A$211,0),MATCH('Расчет грейда'!$AD23,'справочная информация'!$B$187:$Y$187,0))),"НЕТ") | AG23: =VLOOKUP(J23,'справочная информация'!$D$267:$E$274,2,0) -> #N/A | AH23: =VLOOKUP(K23,'справочная информация'!$D$279:$E$283,2,0) -> #N/A | AI23: =VLOOKUP(L23,'справочная информация'!$D$288:$E$290,2,0) -> #N/A | AJ23: =AV23 | AK23: =VLOOKUP(M23,'справочная информация'!$D$294:$E$301,2,0) -> #N/A | AL23: =VLOOKUP(N23,'справочная информация'!$D$306:$E$310,2,0) -> #N/A | AM23: =CONCATENATE("(",AW23,")") -> () | AN23: =AX23 | AO23: =VLOOKUP(O23,'справочная информация'!$D$329:$E$336,2,0) -> #N/A | AP23: =VLOOKUP(P23,'справочная информация'!$D$342:$E$349,2,0) -> #N/A | AQ23: =VLOOKUP(Q23,'справочная информация'!$D$316:$E$325,2,0) -> #N/A | AR23: =AY23 | AS23: =AZ23 | AT23: =IF(AND(AX23="",AY23=""),"",IF(AY23>AX23,"A",IF(AX23=AY23,"L","P"))) | AU23: =ABS(MATCH($AX23,'справочная информация'!$A$354:$A$391,0)-MATCH($AY23,'справочная информация'!$A$354:$A$391,0)) -> #N/A | AV23: =IFERROR(INDEX('справочная информация'!$B$6:$R$29,MATCH('Расчет грейда'!$Y23,'справочная информация'!$A$6:$A$29,0),MATCH('Расчет грейда'!$X23,'справочная информация'!$B$5:$R$5,0)),"") | AW23: =IFERROR(INDEX('справочная информация'!$B$37:$H$52,MATCH('Расчет грейда'!$AA23,'справочная информация'!$A$37:$A$52,0),MATCH('Расчет грейда'!$N23,'справочная информация'!$B$36:$H$36,0)),"") | AX23: =IFERROR(INDEX('справочная информация'!$D$108:$AD$123,MATCH('Расчет грейда'!$AW23,'справочная информация'!$C$108:$C$123,0),MATCH('Расчет грейда'!$AV23,'справочная информация'!$D$107:$AD$107,0)),"") | AY23: =IFERROR(INDEX('справочная информация'!$B$158:$Y$181,MATCH('Расчет грейда'!$AE23,'справочная информация'!$A$158:$A$181,0),MATCH('Расчет грейда'!$AD23,'справочная информация'!$B$157:$Y$157,0)),"") | AZ23: =IFERROR(AV23+AX23+AY23,"") | BA23: =IFERROR(CONCATENATE(TEXT(AZ23/INDEX('справочная информация'!$D$223:$D$261,MATCH('Расчет грейда'!$AZ23,'справочная информация'!$C$223:$C$261,1)),"0%")," - процент относительно медианы 100%. ","MIN балл на грейде ",INDEX('справочная информация'!$C$223:$C$261,MATCH('Расчет грейда'!$AZ23,'справочная информация'!$C$223:$C$261,1)),", "," MAX балл на грейде ",INDEX('справочная информация'!$E$223:$E$261,MATCH('Расчет грейда'!$AZ23,'справочная информация'!$C$223:$C$261,1))),"") | BB23: =IFERROR(IF(AND(AX23="",AY23=""),"",IF(AY23>AX23,"Ответственный профиль (ACC)",IF(AY23=AX23,"Профиль равный (L)","Профиль решения вопросов (PS)"))),"") | BC23: =IFERROR(CONCATENATE(AT23,AU23),"") | BD23: =IFERROR(VLOOKUP(BC23,'справочная информация'!$B$416:$C$424,2,0),"Проверить данные, нетипичная должность") -> Проверить данные, нетипичная должность | BE23: =IFERROR(CONCATENATE(AG23,AH23,AI23," ",AJ23," ",AK23,AL23," ",AM23," ",AN23," ",AO23,AP23,AQ23," ",AR23," ",AS23," ",BC23),"") | BF23: =IFERROR(INDEX('справочная информация'!$F$223:$F$261,MATCH('Расчет грейда'!$AZ23,'справочная информация'!$C$223:$C$261,1)),"")
W24: =IF(IFERROR(BF24-6,"")<0,0,IFERROR(BF24-6,"")) | X24: =CONCATENATE(K24,L24) | Y24: =CONCATENATE(J24,T24) | Z24: =INDEX('справочная информация'!$U$6:$AK$29,MATCH('Расчет грейда'!$Y24,'справочная информация'!$T$6:$T$29,0),MATCH('Расчет грейда'!$X24,'справочная информация'!$U$5:$AK$5,0)) -> #N/A | AA24: =CONCATENATE(M24,U24) | AB24: =INDEX('справочная информация'!$B$68:$H$83,MATCH('Расчет грейда'!$AA24,'справочная информация'!$A$68:$A$83,0),MATCH('Расчет грейда'!$N24,'справочная информация'!$B$67:$H$67,0)) -> #N/A | AC24: =INDEX('справочная информация'!$D$130:$AD$145,MATCH('Расчет грейда'!$AW24,'справочная информация'!$C$130:$C$145,0),MATCH('Расчет грейда'!$AV24,'справочная информация'!$D$129:$AD$129,0)) -> #N/A | AD24: =CONCATENATE(P24,Q24) | AE24: =CONCATENATE(O24,V24) | AF24: =IFERROR(IF(AND(AD24="",AE24=""),"",INDEX('справочная информация'!$B$188:$Y$211,MATCH('Расчет грейда'!$AE24,'справочная информация'!$A$188:$A$211,0),MATCH('Расчет грейда'!$AD24,'справочная информация'!$B$187:$Y$187,0))),"НЕТ") | AG24: =VLOOKUP(J24,'справочная информация'!$D$267:$E$274,2,0) -> #N/A | AH24: =VLOOKUP(K24,'справочная информация'!$D$279:$E$283,2,0) -> #N/A | AI24: =VLOOKUP(L24,'справочная информация'!$D$288:$E$290,2,0) -> #N/A | AJ24: =AV24 | AK24: =VLOOKUP(M24,'справочная информация'!$D$294:$E$301,2,0) -> #N/A | AL24: =VLOOKUP(N24,'справочная информация'!$D$306:$E$310,2,0) -> #N/A | AM24: =CONCATENATE("(",AW24,")") -> () | AN24: =AX24 | AO24: =VLOOKUP(O24,'справочная информация'!$D$329:$E$336,2,0) -> #N/A | AP24: =VLOOKUP(P24,'справочная информация'!$D$342:$E$349,2,0) -> #N/A | AQ24: =VLOOKUP(Q24,'справочная информация'!$D$316:$E$325,2,0) -> #N/A | AR24: =AY24 | AS24: =AZ24 | AT24: =IF(AND(AX24="",AY24=""),"",IF(AY24>AX24,"A",IF(AX24=AY24,"L","P"))) | AU24: =ABS(MATCH($AX24,'справочная информация'!$A$354:$A$391,0)-MATCH($AY24,'справочная информация'!$A$354:$A$391,0)) -> #N/A | AV24: =IFERROR(INDEX('справочная информация'!$B$6:$R$29,MATCH('Расчет грейда'!$Y24,'справочная информация'!$A$6:$A$29,0),MATCH('Расчет грейда'!$X24,'справочная информация'!$B$5:$R$5,0)),"") | AW24: =IFERROR(INDEX('справочная информация'!$B$37:$H$52,MATCH('Расчет грейда'!$AA24,'справочная информация'!$A$37:$A$52,0),MATCH('Расчет грейда'!$N24,'справочная информация'!$B$36:$H$36,0)),"") | AX24: =IFERROR(INDEX('справочная информация'!$D$108:$AD$123,MATCH('Расчет грейда'!$AW24,'справочная информация'!$C$108:$C$123,0),MATCH('Расчет грейда'!$AV24,'справочная информация'!$D$107:$AD$107,0)),"") | AY24: =IFERROR(INDEX('справочная информация'!$B$158:$Y$181,MATCH('Расчет грейда'!$AE24,'справочная информация'!$A$158:$A$181,0),MATCH('Расчет грейда'!$AD24,'справочная информация'!$B$157:$Y$157,0)),"") | AZ24: =IFERROR(AV24+AX24+AY24,"") | BA24: =IFERROR(CONCATENATE(TEXT(AZ24/INDEX('справочная информация'!$D$223:$D$261,MATCH('Расчет грейда'!$AZ24,'справочная информация'!$C$223:$C$261,1)),"0%")," - процент относительно медианы 100%. ","MIN балл на грейде ",INDEX('справочная информация'!$C$223:$C$261,MATCH('Расчет грейда'!$AZ24,'справочная информация'!$C$223:$C$261,1)),", "," MAX балл на грейде ",INDEX('справочная информация'!$E$223:$E$261,MATCH('Расчет грейда'!$AZ24,'справочная информация'!$C$223:$C$261,1))),"") | BB24: =IFERROR(IF(AND(AX24="",AY24=""),"",IF(AY24>AX24,"Ответственный профиль (ACC)",IF(AY24=AX24,"Профиль равный (L)","Профиль решения вопросов (PS)"))),"") | BC24: =IFERROR(CONCATENATE(AT24,AU24),"") | BD24: =IFERROR(VLOOKUP(BC24,'справочная информация'!$B$416:$C$424,2,0),"Проверить данные, нетипичная должность") -> Проверить данные, нетипичная должность | BE24: =IFERROR(CONCATENATE(AG24,AH24,AI24," ",AJ24," ",AK24,AL24," ",AM24," ",AN24," ",AO24,AP24,AQ24," ",AR24," ",AS24," ",BC24),"") | BF24: =IFERROR(INDEX('справочная информация'!$F$223:$F$261,MATCH('Расчет грейда'!$AZ24,'справочная информация'!$C$223:$C$261,1)),"")
W25: =IF(IFERROR(BF25-6,"")<0,0,IFERROR(BF25-6,"")) | X25: =CONCATENATE(K25,L25) | Y25: =CONCATENATE(J25,T25) | Z25: =INDEX('справочная информация'!$U$6:$AK$29,MATCH('Расчет грейда'!$Y25,'справочная информация'!$T$6:$T$29,0),MATCH('Расчет грейда'!$X25,'справочная информация'!$U$5:$AK$5,0)) -> #N/A | AA25: =CONCATENATE(M25,U25) | AB25: =INDEX('справочная информация'!$B$68:$H$83,MATCH('Расчет грейда'!$AA25,'справочная информация'!$A$68:$A$83,0),MATCH('Расчет грейда'!$N25,'справочная информация'!$B$67:$H$67,0)) -> #N/A | AC25: =INDEX('справочная информация'!$D$130:$AD$145,MATCH('Расчет грейда'!$AW25,'справочная информация'!$C$130:$C$145,0),MATCH('Расчет грейда'!$AV25,'справочная информация'!$D$129:$AD$129,0)) -> #N/A | AD25: =CONCATENATE(P25,Q25) | AE25: =CONCATENATE(O25,V25) | AF25: =IFERROR(IF(AND(AD25="",AE25=""),"",INDEX('справочная информация'!$B$188:$Y$211,MATCH('Расчет грейда'!$AE25,'справочная информация'!$A$188:$A$211,0),MATCH('Расчет грейда'!$AD25,'справочная информация'!$B$187:$Y$187,0))),"НЕТ") | AG25: =VLOOKUP(J25,'справочная информация'!$D$267:$E$274,2,0) -> #N/A | AH25: =VLOOKUP(K25,'справочная информация'!$D$279:$E$283,2,0) -> #N/A | AI25: =VLOOKUP(L25,'справочная информация'!$D$288:$E$290,2,0) -> #N/A | AJ25: =AV25 | AK25: =VLOOKUP(M25,'справочная информация'!$D$294:$E$301,2,0) -> #N/A | AL25: =VLOOKUP(N25,'справочная информация'!$D$306:$E$310,2,0) -> #N/A | AM25: =CONCATENATE("(",AW25,")") -> () | AN25: =AX25 | AO25: =VLOOKUP(O25,'справочная информация'!$D$329:$E$336,2,0) -> #N/A | AP25: =VLOOKUP(P25,'справочная информация'!$D$342:$E$349,2,0) -> #N/A | AQ25: =VLOOKUP(Q25,'справочная информация'!$D$316:$E$325,2,0) -> #N/A | AR25: =AY25 | AS25: =AZ25 | AT25: =IF(AND(AX25="",AY25=""),"",IF(AY25>AX25,"A",IF(AX25=AY25,"L","P"))) | AU25: =ABS(MATCH($AX25,'справочная информация'!$A$354:$A$391,0)-MATCH($AY25,'справочная информация'!$A$354:$A$391,0)) -> #N/A | AV25: =IFERROR(INDEX('справочная информация'!$B$6:$R$29,MATCH('Расчет грейда'!$Y25,'справочная информация'!$A$6:$A$29,0),MATCH('Расчет грейда'!$X25,'справочная информация'!$B$5:$R$5,0)),"") | AW25: =IFERROR(INDEX('справочная информация'!$B$37:$H$52,MATCH('Расчет грейда'!$AA25,'справочная информация'!$A$37:$A$52,0),MATCH('Расчет грейда'!$N25,'справочная информация'!$B$36:$H$36,0)),"") | AX25: =IFERROR(INDEX('справочная информация'!$D$108:$AD$123,MATCH('Расчет грейда'!$AW25,'справочная информация'!$C$108:$C$123,0),MATCH('Расчет грейда'!$AV25,'справочная информация'!$D$107:$AD$107,0)),"") | AY25: =IFERROR(INDEX('справочная информация'!$B$158:$Y$181,MATCH('Расчет грейда'!$AE25,'справочная информация'!$A$158:$A$181,0),MATCH('Расчет грейда'!$AD25,'справочная информация'!$B$157:$Y$157,0)),"") | AZ25: =IFERROR(AV25+AX25+AY25,"") | BA25: =IFERROR(CONCATENATE(TEXT(AZ25/INDEX('справочная информация'!$D$223:$D$261,MATCH('Расчет грейда'!$AZ25,'справочная информация'!$C$223:$C$261,1)),"0%")," - процент относительно медианы 100%. ","MIN балл на грейде ",INDEX('справочная информация'!$C$223:$C$261,MATCH('Расчет грейда'!$AZ25,'справочная информация'!$C$223:$C$261,1)),", "," MAX балл на грейде ",INDEX('справочная информация'!$E$223:$E$261,MATCH('Расчет грейда'!$AZ25,'справочная информация'!$C$223:$C$261,1))),"") | BB25: =IFERROR(IF(AND(AX25="",AY25=""),"",IF(AY25>AX25,"Ответственный профиль (ACC)",IF(AY25=AX25,"Профиль равный (L)","Профиль решения вопросов (PS)"))),"") | BC25: =IFERROR(CONCATENATE(AT25,AU25),"") | BD25: =IFERROR(VLOOKUP(BC25,'справочная информация'!$B$416:$C$424,2,0),"Проверить данные, нетипичная должность") -> Проверить данные, нетипичная должность | BE25: =IFERROR(CONCATENATE(AG25,AH25,AI25," ",AJ25," ",AK25,AL25," ",AM25," ",AN25," ",AO25,AP25,AQ25," ",AR25," ",AS25," ",BC25),"") | BF25: =IFERROR(INDEX('справочная информация'!$F$223:$F$261,MATCH('Расчет грейда'!$AZ25,'справочная информация'!$C$223:$C$261,1)),"")
W26: =IF(IFERROR(BF26-6,"")<0,0,IFERROR(BF26-6,"")) | X26: =CONCATENATE(K26,L26) | Y26: =CONCATENATE(J26,T26) | Z26: =INDEX('справочная информация'!$U$6:$AK$29,MATCH('Расчет грейда'!$Y26,'справочная информация'!$T$6:$T$29,0),MATCH('Расчет грейда'!$X26,'справочная информация'!$U$5:$AK$5,0)) -> #N/A | AA26: =CONCATENATE(M26,U26) | AB26: =INDEX('справочная информация'!$B$68:$H$83,MATCH('Расчет грейда'!$AA26,'справочная информация'!$A$68:$A$83,0),MATCH('Расчет грейда'!$N26,'справочная информация'!$B$67:$H$67,0)) -> #N/A | AC26: =INDEX('справочная информация'!$D$130:$AD$145,MATCH('Расчет грейда'!$AW26,'справочная информация'!$C$130:$C$145,0),MATCH('Расчет грейда'!$AV26,'справочная информация'!$D$129:$AD$129,0)) -> #N/A | AD26: =CONCATENATE(P26,Q26) | AE26: =CONCATENATE(O26,V26) | AF26: =IFERROR(IF(AND(AD26="",AE26=""),"",INDEX('справочная информация'!$B$188:$Y$211,MATCH('Расчет грейда'!$AE26,'справочная информация'!$A$188:$A$211,0),MATCH('Расчет грейда'!$AD26,'справочная информация'!$B$187:$Y$187,0))),"НЕТ") | AG26: =VLOOKUP(J26,'справочная информация'!$D$267:$E$274,2,0) -> #N/A | AH26: =VLOOKUP(K26,'справочная информация'!$D$279:$E$283,2,0) -> #N/A | AI26: =VLOOKUP(L26,'справочная информация'!$D$288:$E$290,2,0) -> #N/A | AJ26: =AV26 | AK26: =VLOOKUP(M26,'справочная информация'!$D$294:$E$301,2,0) -> #N/A | AL26: =VLOOKUP(N26,'справочная информация'!$D$306:$E$310,2,0) -> #N/A | AM26: =CONCATENATE("(",AW26,")") -> () | AN26: =AX26 | AO26: =VLOOKUP(O26,'справочная информация'!$D$329:$E$336,2,0) -> #N/A | AP26: =VLOOKUP(P26,'справочная информация'!$D$342:$E$349,2,0) -> #N/A | AQ26: =VLOOKUP(Q26,'справочная информация'!$D$316:$E$325,2,0) -> #N/A | AR26: =AY26 | AS26: =AZ26 | AT26: =IF(AND(AX26="",AY26=""),"",IF(AY26>AX26,"A",IF(AX26=AY26,"L","P"))) | AU26: =ABS(MATCH($AX26,'справочная информация'!$A$354:$A$391,0)-MATCH($AY26,'справочная информация'!$A$354:$A$391,0)) -> #N/A | AV26: =IFERROR(INDEX('справочная информация'!$B$6:$R$29,MATCH('Расчет грейда'!$Y26,'справочная информация'!$A$6:$A$29,0),MATCH('Расчет грейда'!$X26,'справочная информация'!$B$5:$R$5,0)),"") | AW26: =IFERROR(INDEX('справочная информация'!$B$37:$H$52,MATCH('Расчет грейда'!$AA26,'справочная информация'!$A$37:$A$52,0),MATCH('Расчет грейда'!$N26,'справочная информация'!$B$36:$H$36,0)),"") | AX26: =IFERROR(INDEX('справочная информация'!$D$108:$AD$123,MATCH('Расчет грейда'!$AW26,'справочная информация'!$C$108:$C$123,0),MATCH('Расчет грейда'!$AV26,'справочная информация'!$D$107:$AD$107,0)),"") | AY26: =IFERROR(INDEX('справочная информация'!$B$158:$Y$181,MATCH('Расчет грейда'!$AE26,'справочная информация'!$A$158:$A$181,0),MATCH('Расчет грейда'!$AD26,'справочная информация'!$B$157:$Y$157,0)),"") | AZ26: =IFERROR(AV26+AX26+AY26,"") | BA26: =IFERROR(CONCATENATE(TEXT(AZ26/INDEX('справочная информация'!$D$223:$D$261,MATCH('Расчет грейда'!$AZ26,'справочная информация'!$C$223:$C$261,1)),"0%")," - процент относительно медианы 100%. ","MIN балл на грейде ",INDEX('справочная информация'!$C$223:$C$261,MATCH('Расчет грейда'!$AZ26,'справочная информация'!$C$223:$C$261,1)),", "," MAX балл на грейде ",INDEX('справочная информация'!$E$223:$E$261,MATCH('Расчет грейда'!$AZ26,'справочная информация'!$C$223:$C$261,1))),"") | BB26: =IFERROR(IF(AND(AX26="",AY26=""),"",IF(AY26>AX26,"Ответственный профиль (ACC)",IF(AY26=AX26,"Профиль равный (L)","Профиль решения вопросов (PS)"))),"") | BC26: =IFERROR(CONCATENATE(AT26,AU26),"") | BD26: =IFERROR(VLOOKUP(BC26,'справочная информация'!$B$416:$C$424,2,0),"Проверить данные, нетипичная должность") -> Проверить данные, нетипичная должность | BE26: =IFERROR(CONCATENATE(AG26,AH26,AI26," ",AJ26," ",AK26,AL26," ",AM26," ",AN26," ",AO26,AP26,AQ26," ",AR26," ",AS26," ",BC26),"") | BF26: =IFERROR(INDEX('справочная информация'!$F$223:$F$261,MATCH('Расчет грейда'!$AZ26,'справочная информация'!$C$223:$C$261,1)),"")
W27: =IF(IFERROR(BF27-6,"")<0,0,IFERROR(BF27-6,"")) | X27: =CONCATENATE(K27,L27) | Y27: =CONCATENATE(J27,T27) | Z27: =INDEX('справочная информация'!$U$6:$AK$29,MATCH('Расчет грейда'!$Y27,'справочная информация'!$T$6:$T$29,0),MATCH('Расчет грейда'!$X27,'справочная информация'!$U$5:$AK$5,0)) -> #N/A | AA27: =CONCATENATE(M27,U27) | AB27: =INDEX('справочная информация'!$B$68:$H$83,MATCH('Расчет грейда'!$AA27,'справочная информация'!$A$68:$A$83,0),MATCH('Расчет грейда'!$N27,'справочная информация'!$B$67:$H$67,0)) -> #N/A | AC27: =INDEX('справочная информация'!$D$130:$AD$145,MATCH('Расчет грейда'!$AW27,'справочная информация'!$C$130:$C$145,0),MATCH('Расчет грейда'!$AV27,'справочная информация'!$D$129:$AD$129,0)) -> #N/A | AD27: =CONCATENATE(P27,Q27) | AE27: =CONCATENATE(O27,V27) | AF27: =IFERROR(IF(AND(AD27="",AE27=""),"",INDEX('справочная информация'!$B$188:$Y$211,MATCH('Расчет грейда'!$AE27,'справочная информация'!$A$188:$A$211,0),MATCH('Расчет грейда'!$AD27,'справочная информация'!$B$187:$Y$187,0))),"НЕТ") | AG27: =VLOOKUP(J27,'справочная информация'!$D$267:$E$274,2,0) -> #N/A | AH27: =VLOOKUP(K27,'справочная информация'!$D$279:$E$283,2,0) -> #N/A | AI27: =VLOOKUP(L27,'справочная информация'!$D$288:$E$290,2,0) -> #N/A | AJ27: =AV27 | AK27: =VLOOKUP(M27,'справочная информация'!$D$294:$E$301,2,0) -> #N/A | AL27: =VLOOKUP(N27,'справочная информация'!$D$306:$E$310,2,0) -> #N/A | AM27: =CONCATENATE("(",AW27,")") -> () | AN27: =AX27 | AO27: =VLOOKUP(O27,'справочная информация'!$D$329:$E$336,2,0) -> #N/A | AP27: =VLOOKUP(P27,'справочная информация'!$D$342:$E$349,2,0) -> #N/A | AQ27: =VLOOKUP(Q27,'справочная информация'!$D$316:$E$325,2,0) -> #N/A | AR27: =AY27 | AS27: =AZ27 | AT27: =IF(AND(AX27="",AY27=""),"",IF(AY27>AX27,"A",IF(AX27=AY27,"L","P"))) | AU27: =ABS(MATCH($AX27,'справочная информация'!$A$354:$A$391,0)-MATCH($AY27,'справочная информация'!$A$354:$A$391,0)) -> #N/A | AV27: =IFERROR(INDEX('справочная информация'!$B$6:$R$29,MATCH('Расчет грейда'!$Y27,'справочная информация'!$A$6:$A$29,0),MATCH('Расчет грейда'!$X27,'справочная информация'!$B$5:$R$5,0)),"") | AW27: =IFERROR(INDEX('справочная информация'!$B$37:$H$52,MATCH('Расчет грейда'!$AA27,'справочная информация'!$A$37:$A$52,0),MATCH('Расчет грейда'!$N27,'справочная информация'!$B$36:$H$36,0)),"") | AX27: =IFERROR(INDEX('справочная информация'!$D$108:$AD$123,MATCH('Расчет грейда'!$AW27,'справочная информация'!$C$108:$C$123,0),MATCH('Расчет грейда'!$AV27,'справочная информация'!$D$107:$AD$107,0)),"") | AY27: =IFERROR(INDEX('справочная информация'!$B$158:$Y$181,MATCH('Расчет грейда'!$AE27,'справочная информация'!$A$158:$A$181,0),MATCH('Расчет грейда'!$AD27,'справочная информация'!$B$157:$Y$157,0)),"") | AZ27: =IFERROR(AV27+AX27+AY27,"") | BA27: =IFERROR(CONCATENATE(TEXT(AZ27/INDEX('справочная информация'!$D$223:$D$261,MATCH('Расчет грейда'!$AZ27,'справочная информация'!$C$223:$C$261,1)),"0%")," - процент относительно медианы 100%. ","MIN балл на грейде ",INDEX('справочная информация'!$C$223:$C$261,MATCH('Расчет грейда'!$AZ27,'справочная информация'!$C$223:$C$261,1)),", "," MAX балл на грейде ",INDEX('справочная информация'!$E$223:$E$261,MATCH('Расчет грейда'!$AZ27,'справочная информация'!$C$223:$C$261,1))),"") | BB27: =IFERROR(IF(AND(AX27="",AY27=""),"",IF(AY27>AX27,"Ответственный профиль (ACC)",IF(AY27=AX27,"Профиль равный (L)","Профиль решения вопросов (PS)"))),"") | BC27: =IFERROR(CONCATENATE(AT27,AU27),"") | BD27: =IFERROR(VLOOKUP(BC27,'справочная информация'!$B$416:$C$424,2,0),"Проверить данные, нетипичная должность") -> Проверить данные, нетипичная должность | BE27: =IFERROR(CONCATENATE(AG27,AH27,AI27," ",AJ27," ",AK27,AL27," ",AM27," ",AN27," ",AO27,AP27,AQ27," ",AR27," ",AS27," ",BC27),"") | BF27: =IFERROR(INDEX('справочная информация'!$F$223:$F$261,MATCH('Расчет грейда'!$AZ27,'справочная информация'!$C$223:$C$261,1)),"")
W28: =IF(IFERROR(BF28-6,"")<0,0,IFERROR(BF28-6,"")) | X28: =CONCATENATE(K28,L28) | Y28: =CONCATENATE(J28,T28) | Z28: =INDEX('справочная информация'!$U$6:$AK$29,MATCH('Расчет грейда'!$Y28,'справочная информация'!$T$6:$T$29,0),MATCH('Расчет грейда'!$X28,'справочная информация'!$U$5:$AK$5,0)) -> #N/A | AA28: =CONCATENATE(M28,U28) | AB28: =INDEX('справочная информация'!$B$68:$H$83,MATCH('Расчет грейда'!$AA28,'справочная информация'!$A$68:$A$83,0),MATCH('Расчет грейда'!$N28,'справочная информация'!$B$67:$H$67,0)) -> #N/A | AC28: =INDEX('справочная информация'!$D$130:$AD$145,MATCH('Расчет грейда'!$AW28,'справочная информация'!$C$130:$C$145,0),MATCH('Расчет грейда'!$AV28,'справочная информация'!$D$129:$AD$129,0)) -> #N/A | AD28: =CONCATENATE(P28,Q28) | AE28: =CONCATENATE(O28,V28) | AF28: =IFERROR(IF(AND(AD28="",AE28=""),"",INDEX('справочная информация'!$B$188:$Y$211,MATCH('Расчет грейда'!$AE28,'справочная информация'!$A$188:$A$211,0),MATCH('Расчет грейда'!$AD28,'справочная информация'!$B$187:$Y$187,0))),"НЕТ") | AG28: =VLOOKUP(J28,'справочная информация'!$D$267:$E$274,2,0) -> #N/A | AH28: =VLOOKUP(K28,'справочная информация'!$D$279:$E$283,2,0) -> #N/A | AI28: =VLOOKUP(L28,'справочная информация'!$D$288:$E$290,2,0) -> #N/A | AJ28: =AV28 | AK28: =VLOOKUP(M28,'справочная информация'!$D$294:$E$301,2,0) -> #N/A | AL28: =VLOOKUP(N28,'справочная информация'!$D$306:$E$310,2,0) -> #N/A | AM28: =CONCATENATE("(",AW28,")") -> () | AN28: =AX28 | AO28: =VLOOKUP(O28,'справочная информация'!$D$329:$E$336,2,0) -> #N/A | AP28: =VLOOKUP(P28,'справочная информация'!$D$342:$E$349,2,0) -> #N/A | AQ28: =VLOOKUP(Q28,'справочная информация'!$D$316:$E$325,2,0) -> #N/A | AR28: =AY28 | AS28: =AZ28 | AT28: =IF(AND(AX28="",AY28=""),"",IF(AY28>AX28,"A",IF(AX28=AY28,"L","P"))) | AU28: =ABS(MATCH($AX28,'справочная информация'!$A$354:$A$391,0)-MATCH($AY28,'справочная информация'!$A$354:$A$391,0)) -> #N/A | AV28: =IFERROR(INDEX('справочная информация'!$B$6:$R$29,MATCH('Расчет грейда'!$Y28,'справочная информация'!$A$6:$A$29,0),MATCH('Расчет грейда'!$X28,'справочная информация'!$B$5:$R$5,0)),"") | AW28: =IFERROR(INDEX('справочная информация'!$B$37:$H$52,MATCH('Расчет грейда'!$AA28,'справочная информация'!$A$37:$A$52,0),MATCH('Расчет грейда'!$N28,'справочная информация'!$B$36:$H$36,0)),"") | AX28: =IFERROR(INDEX('справочная информация'!$D$108:$AD$123,MATCH('Расчет грейда'!$AW28,'справочная информация'!$C$108:$C$123,0),MATCH('Расчет грейда'!$AV28,'справочная информация'!$D$107:$AD$107,0)),"") | AY28: =IFERROR(INDEX('справочная информация'!$B$158:$Y$181,MATCH('Расчет грейда'!$AE28,'справочная информация'!$A$158:$A$181,0),MATCH('Расчет грейда'!$AD28,'справочная информация'!$B$157:$Y$157,0)),"") | AZ28: =IFERROR(AV28+AX28+AY28,"") | BA28: =IFERROR(CONCATENATE(TEXT(AZ28/INDEX('справочная информация'!$D$223:$D$261,MATCH('Расчет грейда'!$AZ28,'справочная информация'!$C$223:$C$261,1)),"0%")," - процент относительно медианы 100%. ","MIN балл на грейде ",INDEX('справочная информация'!$C$223:$C$261,MATCH('Расчет грейда'!$AZ28,'справочная информация'!$C$223:$C$261,1)),", "," MAX балл на грейде ",INDEX('справочная информация'!$E$223:$E$261,MATCH('Расчет грейда'!$AZ28,'справочная информация'!$C$223:$C$261,1))),"") | BB28: =IFERROR(IF(AND(AX28="",AY28=""),"",IF(AY28>AX28,"Ответственный профиль (ACC)",IF(AY28=AX28,"Профиль равный (L)","Профиль решения вопросов (PS)"))),"") | BC28: =IFERROR(CONCATENATE(AT28,AU28),"") | BD28: =IFERROR(VLOOKUP(BC28,'справочная информация'!$B$416:$C$424,2,0),"Проверить данные, нетипичная должность") -> Проверить данные, нетипичная должность | BE28: =IFERROR(CONCATENATE(AG28,AH28,AI28," ",AJ28," ",AK28,AL28," ",AM28," ",AN28," ",AO28,AP28,AQ28," ",AR28," ",AS28," ",BC28),"") | BF28: =IFERROR(INDEX('справочная информация'!$F$223:$F$261,MATCH('Расчет грейда'!$AZ28,'справочная информация'!$C$223:$C$261,1)),"")
W29: =IF(IFERROR(BF29-6,"")<0,0,IFERROR(BF29-6,"")) | X29: =CONCATENATE(K29,L29) | Y29: =CONCATENATE(J29,T29) | Z29: =INDEX('справочная информация'!$U$6:$AK$29,MATCH('Расчет грейда'!$Y29,'справочная информация'!$T$6:$T$29,0),MATCH('Расчет грейда'!$X29,'справочная информация'!$U$5:$AK$5,0)) -> #N/A | AA29: =CONCATENATE(M29,U29) | AB29: =INDEX('справочная информация'!$B$68:$H$83,MATCH('Расчет грейда'!$AA29,'справочная информация'!$A$68:$A$83,0),MATCH('Расчет грейда'!$N29,'справочная информация'!$B$67:$H$67,0)) -> #N/A | AC29: =INDEX('справочная информация'!$D$130:$AD$145,MATCH('Расчет грейда'!$AW29,'справочная информация'!$C$130:$C$145,0),MATCH('Расчет грейда'!$AV29,'справочная информация'!$D$129:$AD$129,0)) -> #N/A | AD29: =CONCATENATE(P29,Q29) | AE29: =CONCATENATE(O29,V29) | AF29: =IFERROR(IF(AND(AD29="",AE29=""),"",INDEX('справочная информация'!$B$188:$Y$211,MATCH('Расчет грейда'!$AE29,'справочная информация'!$A$188:$A$211,0),MATCH('Расчет грейда'!$AD29,'справочная информация'!$B$187:$Y$187,0))),"НЕТ") | AG29: =VLOOKUP(J29,'справочная информация'!$D$267:$E$274,2,0) -> #N/A | AH29: =VLOOKUP(K29,'справочная информация'!$D$279:$E$283,2,0) -> #N/A | AI29: =VLOOKUP(L29,'справочная информация'!$D$288:$E$290,2,0) -> #N/A | AJ29: =AV29 | AK29: =VLOOKUP(M29,'справочная информация'!$D$294:$E$301,2,0) -> #N/A | AL29: =VLOOKUP(N29,'справочная информация'!$D$306:$E$310,2,0) -> #N/A | AM29: =CONCATENATE("(",AW29,")") -> () | AN29: =AX29 | AO29: =VLOOKUP(O29,'справочная информация'!$D$329:$E$336,2,0) -> #N/A | AP29: =VLOOKUP(P29,'справочная информация'!$D$342:$E$349,2,0) -> #N/A | AQ29: =VLOOKUP(Q29,'справочная информация'!$D$316:$E$325,2,0) -> #N/A | AR29: =AY29 | AS29: =AZ29 | AT29: =IF(AND(AX29="",AY29=""),"",IF(AY29>AX29,"A",IF(AX29=AY29,"L","P"))) | AU29: =ABS(MATCH($AX29,'справочная информация'!$A$354:$A$391,0)-MATCH($AY29,'справочная информация'!$A$354:$A$391,0)) -> #N/A | AV29: =IFERROR(INDEX('справочная информация'!$B$6:$R$29,MATCH('Расчет грейда'!$Y29,'справочная информация'!$A$6:$A$29,0),MATCH('Расчет грейда'!$X29,'справочная информация'!$B$5:$R$5,0)),"") | AW29: =IFERROR(INDEX('справочная информация'!$B$37:$H$52,MATCH('Расчет грейда'!$AA29,'справочная информация'!$A$37:$A$52,0),MATCH('Расчет грейда'!$N29,'справочная информация'!$B$36:$H$36,0)),"") | AX29: =IFERROR(INDEX('справочная информация'!$D$108:$AD$123,MATCH('Расчет грейда'!$AW29,'справочная информация'!$C$108:$C$123,0),MATCH('Расчет грейда'!$AV29,'справочная информация'!$D$107:$AD$107,0)),"") | AY29: =IFERROR(INDEX('справочная информация'!$B$158:$Y$181,MATCH('Расчет грейда'!$AE29,'справочная информация'!$A$158:$A$181,0),MATCH('Расчет грейда'!$AD29,'справочная информация'!$B$157:$Y$157,0)),"") | AZ29: =IFERROR(AV29+AX29+AY29,"") | BA29: =IFERROR(CONCATENATE(TEXT(AZ29/INDEX('справочная информация'!$D$223:$D$261,MATCH('Расчет грейда'!$AZ29,'справочная информация'!$C$223:$C$261,1)),"0%")," - процент относительно медианы 100%. ","MIN балл на грейде ",INDEX('справочная информация'!$C$223:$C$261,MATCH('Расчет грейда'!$AZ29,'справочная информация'!$C$223:$C$261,1)),", "," MAX балл на грейде ",INDEX('справочная информация'!$E$223:$E$261,MATCH('Расчет грейда'!$AZ29,'справочная информация'!$C$223:$C$261,1))),"") | BB29: =IFERROR(IF(AND(AX29="",AY29=""),"",IF(AY29>AX29,"Ответственный профиль (ACC)",IF(AY29=AX29,"Профиль равный (L)","Профиль решения вопросов (PS)"))),"") | BC29: =IFERROR(CONCATENATE(AT29,AU29),"") | BD29: =IFERROR(VLOOKUP(BC29,'справочная информация'!$B$416:$C$424,2,0),"Проверить данные, нетипичная должность") -> Проверить данные, нетипичная должность | BE29: =IFERROR(CONCATENATE(AG29,AH29,AI29," ",AJ29," ",AK29,AL29," ",AM29," ",AN29," ",AO29,AP29,AQ29," ",AR29," ",AS29," ",BC29),"") | BF29: =IFERROR(INDEX('справочная информация'!$F$223:$F$261,MATCH('Расчет грейда'!$AZ29,'справочная информация'!$C$223:$C$261,1)),"")
W30: =IF(IFERROR(BF30-6,"")<0,0,IFERROR(BF30-6,"")) | X30: =CONCATENATE(K30,L30) | Y30: =CONCATENATE(J30,T30) | Z30: =INDEX('справочная информация'!$U$6:$AK$29,MATCH('Расчет грейда'!$Y30,'справочная информация'!$T$6:$T$29,0),MATCH('Расчет грейда'!$X30,'справочная информация'!$U$5:$AK$5,0)) -> #N/A | AA30: =CONCATENATE(M30,U30) | AB30: =INDEX('справочная информация'!$B$68:$H$83,MATCH('Расчет грейда'!$AA30,'справочная информация'!$A$68:$A$83,0),MATCH('Расчет грейда'!$N30,'справочная информация'!$B$67:$H$67,0)) -> #N/A | AC30: =INDEX('справочная информация'!$D$130:$AD$145,MATCH('Расчет грейда'!$AW30,'справочная информация'!$C$130:$C$145,0),MATCH('Расчет грейда'!$AV30,'справочная информация'!$D$129:$AD$129,0)) -> #N/A | AD30: =CONCATENATE(P30,Q30) | AE30: =CONCATENATE(O30,V30) | AF30: =IFERROR(IF(AND(AD30="",AE30=""),"",INDEX('справочная информация'!$B$188:$Y$211,MATCH('Расчет грейда'!$AE30,'справочная информация'!$A$188:$A$211,0),MATCH('Расчет грейда'!$AD30,'справочная информация'!$B$187:$Y$187,0))),"НЕТ") | AG30: =VLOOKUP(J30,'справочная информация'!$D$267:$E$274,2,0) -> #N/A | AH30: =VLOOKUP(K30,'справочная информация'!$D$279:$E$283,2,0) -> #N/A | AI30: =VLOOKUP(L30,'справочная информация'!$D$288:$E$290,2,0) -> #N/A | AJ30: =AV30 | AK30: =VLOOKUP(M30,'справочная информация'!$D$294:$E$301,2,0) -> #N/A | AL30: =VLOOKUP(N30,'справочная информация'!$D$306:$E$310,2,0) -> #N/A | AM30: =CONCATENATE("(",AW30,")") -> () | AN30: =AX30 | AO30: =VLOOKUP(O30,'справочная информация'!$D$329:$E$336,2,0) -> #N/A | AP30: =VLOOKUP(P30,'справочная информация'!$D$342:$E$349,2,0) -> #N/A | AQ30: =VLOOKUP(Q30,'справочная информация'!$D$316:$E$325,2,0) -> #N/A | AR30: =AY30 | AS30: =AZ30 | AT30: =IF(AND(AX30="",AY30=""),"",IF(AY30>AX30,"A",IF(AX30=AY30,"L","P"))) | AU30: =ABS(MATCH($AX30,'справочная информация'!$A$354:$A$391,0)-MATCH($AY30,'справочная информация'!$A$354:$A$391,0)) -> #N/A | AV30: =IFERROR(INDEX('справочная информация'!$B$6:$R$29,MATCH('Расчет грейда'!$Y30,'справочная информация'!$A$6:$A$29,0),MATCH('Расчет грейда'!$X30,'справочная информация'!$B$5:$R$5,0)),"") | AW30: =IFERROR(INDEX('справочная информация'!$B$37:$H$52,MATCH('Расчет грейда'!$AA30,'справочная информация'!$A$37:$A$52,0),MATCH('Расчет грейда'!$N30,'справочная информация'!$B$36:$H$36,0)),"") | AX30: =IFERROR(INDEX('справочная информация'!$D$108:$AD$123,MATCH('Расчет грейда'!$AW30,'справочная информация'!$C$108:$C$123,0),MATCH('Расчет грейда'!$AV30,'справочная информация'!$D$107:$AD$107,0)),"") | AY30: =IFERROR(INDEX('справочная информация'!$B$158:$Y$181,MATCH('Расчет грейда'!$AE30,'справочная информация'!$A$158:$A$181,0),MATCH('Расчет грейда'!$AD30,'справочная информация'!$B$157:$Y$157,0)),"") | AZ30: =IFERROR(AV30+AX30+AY30,"") | BA30: =IFERROR(CONCATENATE(TEXT(AZ30/INDEX('справочная информация'!$D$223:$D$261,MATCH('Расчет грейда'!$AZ30,'справочная информация'!$C$223:$C$261,1)),"0%")," - процент относительно медианы 100%. ","MIN балл на грейде ",INDEX('справочная информация'!$C$223:$C$261,MATCH('Расчет грейда'!$AZ30,'справочная информация'!$C$223:$C$261,1)),", "," MAX балл на грейде ",INDEX('справочная информация'!$E$223:$E$261,MATCH('Расчет грейда'!$AZ30,'справочная информация'!$C$223:$C$261,1))),"") | BB30: =IFERROR(IF(AND(AX30="",AY30=""),"",IF(AY30>AX30,"Ответственный профиль (ACC)",IF(AY30=AX30,"Профиль равный (L)","Профиль решения вопросов (PS)"))),"") | BC30: =IFERROR(CONCATENATE(AT30,AU30),"") | BD30: =IFERROR(VLOOKUP(BC30,'справочная информация'!$B$416:$C$424,2,0),"Проверить данные, нетипичная должность") -> Проверить данные, нетипичная должность | BE30: =IFERROR(CONCATENATE(AG30,AH30,AI30," ",AJ30," ",AK30,AL30," ",AM30," ",AN30," ",AO30,AP30,AQ30," ",AR30," ",AS30," ",BC30),"") | BF30: =IFERROR(INDEX('справочная информация'!$F$223:$F$261,MATCH('Расчет грейда'!$AZ30,'справочная информация'!$C$223:$C$261,1)),"")
... W185: =IF(IFERROR(BF185-6,"")<0,0,IFERROR(BF185-6,"")) | X185: =CONCATENATE(K185,L185) | Y185: =CONCATENATE(J185,T185) | Z185: =INDEX('справочная информация'!$U$6:$AK$29,MATCH('Расчет грейда'!$Y185,'справочная информация'!$T$6:$T$29,0),MATCH('Расчет грейда'!$X185,'справочная информация'!$U$5:$AK$5,0)) -> #N/A | AA185: =CONCATENATE(M185,U185) | AB185: =INDEX('справочная информация'!$B$68:$H$83,MATCH('Расчет грейда'!$AA185,'справочная информация'!$A$68:$A$83,0),MATCH('Расчет грейда'!$N185,'справочная информация'!$B$67:$H$67,0)) -> #N/A | AC185: =INDEX('справочная информация'!$D$130:$AD$145,MATCH('Расчет грейда'!$AW185,'справочная информация'!$C$130:$C$145,0),MATCH('Расчет грейда'!$AV185,'справочная информация'!$D$129:$AD$129,0)) -> #N/A | AD185: =CONCATENATE(P185,Q185) | AE185: =CONCATENATE(O185,V185) | AF185: =IFERROR(IF(AND(AD185="",AE185=""),"",INDEX('справочная информация'!$B$188:$Y$211,MATCH('Расчет грейда'!$AE185,'справочная информация'!$A$188:$A$211,0),MATCH('Расчет грейда'!$AD185,'справочная информация'!$B$187:$Y$187,0))),"НЕТ") | AG185: =VLOOKUP(J185,'справочная информация'!$D$267:$E$274,2,0) -> #N/A | AH185: =VLOOKUP(K185,'справочная информация'!$D$279:$E$283,2,0) -> #N/A | AI185: =VLOOKUP(L185,'справочная информация'!$D$288:$E$290,2,0) -> #N/A | AJ185: =AV185 | AK185: =VLOOKUP(M185,'справочная информация'!$D$294:$E$301,2,0) -> #N/A | AL185: =VLOOKUP(N185,'справочная информация'!$D$306:$E$310,2,0) -> #N/A | AM185: =CONCATENATE("(",AW185,")") -> () | AN185: =AX185 | AO185: =VLOOKUP(O185,'справочная информация'!$D$329:$E$336,2,0) -> #N/A | AP185: =VLOOKUP(P185,'справочная информация'!$D$342:$E$349,2,0) -> #N/A | AQ185: =VLOOKUP(Q185,'справочная информация'!$D$316:$E$325,2,0) -> #N/A | AR185: =AY185 | AS185: =AZ185 | AT185: =IF(AND(AX185="",AY185=""),"",IF(AY185>AX185,"A",IF(AX185=AY185,"L","P"))) | AU185: =ABS(MATCH($AX185,'справочная информация'!$A$354:$A$391,0)-MATCH($AY185,'справочная информация'!$A$354:$A$391,0)) -> #N/A | AV185: =IFERROR(INDEX('справочная информация'!$B$6:$R$29,MATCH('Расчет грейда'!$Y185,'справочная информация'!$A$6:$A$29,0),MATCH('Расчет грейда'!$X185,'справочная информация'!$B$5:$R$5,0)),"") | AW185: =IFERROR(INDEX('справочная информация'!$B$37:$H$52,MATCH('Расчет грейда'!$AA185,'справочная информация'!$A$37:$A$52,0),MATCH('Расчет грейда'!$N185,'справочная информация'!$B$36:$H$36,0)),"") | AX185: =IFERROR(INDEX('справочная информация'!$D$108:$AD$123,MATCH('Расчет грейда'!$AW185,'справочная информация'!$C$108:$C$123,0),MATCH('Расчет грейда'!$AV185,'справочная информация'!$D$107:$AD$107,0)),"") | AY185: =IFERROR(INDEX('справочная информация'!$B$158:$Y$181,MATCH('Расчет грейда'!$AE185,'справочная информация'!$A$158:$A$181,0),MATCH('Расчет грейда'!$AD185,'справочная информация'!$B$157:$Y$157,0)),"") | AZ185: =IFERROR(AV185+AX185+AY185,"") | BA185: =IFERROR(CONCATENATE(TEXT(AZ185/INDEX('справочная информация'!$D$223:$D$261,MATCH('Расчет грейда'!$AZ185,'справочная информация'!$C$223:$C$261,1)),"0%")," - процент относительно медианы 100%. ","MIN балл на грейде ",INDEX('справочная информация'!$C$223:$C$261,MATCH('Расчет грейда'!$AZ185,'справочная информация'!$C$223:$C$261,1)),", "," MAX балл на грейде ",INDEX('справочная информация'!$E$223:$E$261,MATCH('Расчет грейда'!$AZ185,'справочная информация'!$C$223:$C$261,1))),"") | BB185: =IFERROR(IF(AND(AX185="",AY185=""),"",IF(AY185>AX185,"Ответственный профиль (ACC)",IF(AY185=AX185,"Профиль равный (L)","Профиль решения вопросов (PS)"))),"") | BC185: =IFERROR(CONCATENATE(AT185,AU185),"") | BD185: =IFERROR(VLOOKUP(BC185,'справочная информация'!$B$416:$C$424,2,0),"Проверить данные, нетипичная должность") -> Проверить данные, нетипичная должность | BE185: =IFERROR(CONCATENATE(AG185,AH185,AI185," ",AJ185," ",AK185,AL185," ",AM185," ",AN185," ",AO185,AP185,AQ185," ",AR185," ",AS185," ",BC185),"") | BF185: =IFERROR(INDEX('справочная информация'!$F$223:$F$261,MATCH('Расчет грейда'!$AZ185,'справочная информация'!$C$223:$C$261,1)),"")

Sheet ТРС общая
D2: 1 | E2: 2 | F2: 3 | G2: 4 | H2: 5 | I2: 6 | J2: 7 | K2: 8 | L2: 9 | M2: 10 | N2: 11 | O2: 12 | P2: 13 | Q2: 14 | R2: 15 | S2: 16 | T2: 17 | U2: 18 | V2: 19 | W2: 20 | X2: 21 | Y2: 22 | Z2: 23 | AA2: 24 | AB2: 25 | AC2: 26 | AD2: 27 | AE2: 28 | AF2: 29 | AG2: 30 | AH2: 31 | AI2: 32 | AJ2: 33
B6: AS IS
B7: Грейд | C7: Кол-во ролей
B8: 20 | C8: =COUNTIF('Расчет грейда'!$W:$W,'ТРС общая'!$B8) -> 0 | D8: {=IFERROR(INDEX(#REF!,SMALL(IF('ТРС общая'!$B8=#REF!,ROW(#REF!)-18,""),ROW()-(ROW()-D$2))),"")} | E8: {=IFERROR(INDEX(#REF!,SMALL(IF('ТРС общая'!$B8=#REF!,ROW(#REF!)-18,""),ROW()-(ROW()-E$2))),"")} | F8: {=IFERROR(INDEX(#REF!,SMALL(IF('ТРС общая'!$B8=#REF!,ROW(#REF!)-18,""),ROW()-(ROW()-F$2))),"")} | G8: {=IFERROR(INDEX(#REF!,SMALL(IF('ТРС общая'!$B8=#REF!,ROW(#REF!)-18,""),ROW()-(ROW()-G$2))),"")} | H8: {=IFERROR(INDEX(#REF!,SMALL(IF('ТРС общая'!$B8=#REF!,ROW(#REF!)-18,""),ROW()-(ROW()-H$2))),"")} | I8: {=IFERROR(INDEX(#REF!,SMALL(IF('ТРС общая'!$B8=#REF!,ROW(#REF!)-18,""),ROW()-(ROW()-I$2))),"")} | J8: {=IFERROR(INDEX(#REF!,SMALL(IF('ТРС общая'!$B8=#REF!,ROW(#REF!)-18,""),ROW()-(ROW()-J$2))),"")} | K8: {=IFERROR(INDEX(#REF!,SMALL(IF('ТРС общая'!$B8=#REF!,ROW(#REF!)-18,""),ROW()-(ROW()-K$2))),"")} | ... AM8: {=IFERROR(INDEX(#REF!,SMALL(IF('ТРС общая'!$B8=#REF!,ROW(#REF!)-18,""),ROW()-(ROW()-AM$2))),"")}
B9: 19 | C9: =COUNTIF('Расчет грейда'!$W:$W,'ТРС общая'!$B9) -> 0 | D9: {=IFERROR(INDEX(#REF!,SMALL(IF('ТРС общая'!$B9=#REF!,ROW(#REF!)-18,""),ROW()-(ROW()-D$2))),"")} | E9: {=IFERROR(INDEX(#REF!,SMALL(IF('ТРС общая'!$B9=#REF!,ROW(#REF!)-18,""),ROW()-(ROW()-E$2))),"")} | F9: {=IFERROR(INDEX(#REF!,SMALL(IF('ТРС общая'!$B9=#REF!,ROW(#REF!)-18,""),ROW()-(ROW()-F$2))),"")} | G9: {=IFERROR(INDEX(#REF!,SMALL(IF('ТРС общая'!$B9=#REF!,ROW(#REF!)-18,""),ROW()-(ROW()-G$2))),"")} | H9: {=IFERROR(INDEX(#REF!,SMALL(IF('ТРС общая'!$B9=#REF!,ROW(#REF!)-18,""),ROW()-(ROW()-H$2))),"")} | I9: {=IFERROR(INDEX(#REF!,SMALL(IF('ТРС общая'!$B9=#REF!,ROW(#REF!)-18,""),ROW()-(ROW()-I$2))),"")} | J9: {=IFERROR(INDEX(#REF!,SMALL(IF('ТРС общая'!$B9=#REF!,ROW(#REF!)-18,""),ROW()-(ROW()-J$2))),"")} | K9: {=IFERROR(INDEX(#REF!,SMALL(IF('ТРС общая'!$B9=#REF!,ROW(#REF!)-18,""),ROW()-(ROW()-K$2))),"")} | ... AM9: {=IFERROR(INDEX(#REF!,SMALL(IF('ТРС общая'!$B9=#REF!,ROW(#REF!)-18,""),ROW()-(ROW()-AM$2))),"")}
B10: 18 | C10: =COUNTIF('Расчет грейда'!$W:$W,'ТРС общая'!$B10) -> 0 | D10: {=IFERROR(INDEX(#REF!,SMALL(IF('ТРС общая'!$B10=#REF!,ROW(#REF!)-18,""),ROW()-(ROW()-D$2))),"")} | E10: {=IFERROR(INDEX(#REF!,SMALL(IF('ТРС общая'!$B10=#REF!,ROW(#REF!)-18,""),ROW()-(ROW()-E$2))),"")} | F10: {=IFERROR(INDEX(#REF!,SMALL(IF('ТРС общая'!$B10=#REF!,ROW(#REF!)-18,""),ROW()-(ROW()-F$2))),"")} | G10: {=IFERROR(INDEX(#REF!,SMALL(IF('ТРС общая'!$B10=#REF!,ROW(#REF!)-18,""),ROW()-(ROW()-G$2))),"")} | H10: {=IFERROR(INDEX(#REF!,SMALL(IF('ТРС общая'!$B10=#REF!,ROW(#REF!)-18,""),ROW()-(ROW()-H$2))),"")} | I10: {=IFERROR(INDEX(#REF!,SMALL(IF('ТРС общая'!$B10=#REF!,ROW(#REF!)-18,""),ROW()-(ROW()-I$2))),"")} | J10: {=IFERROR(INDEX(#REF!,SMALL(IF('ТРС общая'!$B10=#REF!,ROW(#REF!)-18,""),ROW()-(ROW()-J$2))),"")} | K10: {=IFERROR(INDEX(#REF!,SMALL(IF('ТРС общая'!$B10=#REF!,ROW(#REF!)-18,""),ROW()-(ROW()-K$2))),"")} | ... AM10: {=IFERROR(INDEX(#REF!,SMALL(IF('ТРС общая'!$B10=#REF!,ROW(#REF!)-18,""),ROW()-(ROW()-AM$2))),"")}
B11: 17 | C11: =COUNTIF('Расчет грейда'!$W:$W,'ТРС общая'!$B11) -> 0 | D11: {=IFERROR(INDEX(#REF!,SMALL(IF('ТРС общая'!$B11=#REF!,ROW(#REF!)-18,""),ROW()-(ROW()-D$2))),"")} | E11: {=IFERROR(INDEX(#REF!,SMALL(IF('ТРС общая'!$B11=#REF!,ROW(#REF!)-18,""),ROW()-(ROW()-E$2))),"")} | F11: {=IFERROR(INDEX(#REF!,SMALL(IF('ТРС общая'!$B11=#REF!,ROW(#REF!)-18,""),ROW()-(ROW()-F$2))),"")} | G11: {=IFERROR(INDEX(#REF!,SMALL(IF('ТРС общая'!$B11=#REF!,ROW(#REF!)-18,""),ROW()-(ROW()-G$2))),"")} | H11: {=IFERROR(INDEX(#REF!,SMALL(IF('ТРС общая'!$B11=#REF!,ROW(#REF!)-18,""),ROW()-(ROW()-H$2))),"")} | I11: {=IFERROR(INDEX(#REF!,SMALL(IF('ТРС общая'!$B11=#REF!,ROW(#REF!)-18,""),ROW()-(ROW()-I$2))),"")} | J11: {=IFERROR(INDEX(#REF!,SMALL(IF('ТРС общая'!$B11=#REF!,ROW(#REF!)-18,""),ROW()-(ROW()-J$2))),"")} | K11: {=IFERROR(INDEX(#REF!,SMALL(IF('ТРС общая'!$B11=#REF!,ROW(#REF!)-18,""),ROW()-(ROW()-K$2))),"")} | ... AM11: {=IFERROR(INDEX(#REF!,SMALL(IF('ТРС общая'!$B11=#REF!,ROW(#REF!)-18,""),ROW()-(ROW()-AM$2))),"")}
B12: 16 | C12: =COUNTIF('Расчет грейда'!$W:$W,'ТРС общая'!$B12) -> 0 | D12: {=IFERROR(INDEX(#REF!,SMALL(IF('ТРС общая'!$B12=#REF!,ROW(#REF!)-18,""),ROW()-(ROW()-D$2))),"")} | E12: {=IFERROR(INDEX(#REF!,SMALL(IF('ТРС общая'!$B12=#REF!,ROW(#REF!)-18,""),ROW()-(ROW()-E$2))),"")} | F12: {=IFERROR(INDEX(#REF!,SMALL(IF('ТРС общая'!$B12=#REF!,ROW(#REF!)-18,""),ROW()-(ROW()-F$2))),"")} | G12: {=IFERROR(INDEX(#REF!,SMALL(IF('ТРС общая'!$B12=#REF!,ROW(#REF!)-18,""),ROW()-(ROW()-G$2))),"")} | H12: {=IFERROR(INDEX(#REF!,SMALL(IF('ТРС общая'!$B12=#REF!,ROW(#REF!)-18,""),ROW()-(ROW()-H$2))),"")} | I12: {=IFERROR(INDEX(#REF!,SMALL(IF('ТРС общая'!$B12=#REF!,ROW(#REF!)-18,""),ROW()-(ROW()-I$2))),"")} | J12: {=IFERROR(INDEX(#REF!,SMALL(IF('ТРС общая'!$B12=#REF!,ROW(#REF!)-18,""),ROW()-(ROW()-J$2))),"")} | K12: {=IFERROR(INDEX(#REF!,SMALL(IF('ТРС общая'!$B12=#REF!,ROW(#REF!)-18,""),ROW()-(ROW()-K$2))),"")} | ... AM12: {=IFERROR(INDEX(#REF!,SMALL(IF('ТРС общая'!$B12=#REF!,ROW(#REF!)-18,""),ROW()-(ROW()-AM$2))),"")}
B13: 15 | C13: =COUNTIF('Расчет грейда'!$W:$W,'ТРС общая'!$B13) -> 0 | D13: {=IFERROR(INDEX(#REF!,SMALL(IF('ТРС общая'!$B13=#REF!,ROW(#REF!)-18,""),ROW()-(ROW()-D$2))),"")} | E13: {=IFERROR(INDEX(#REF!,SMALL(IF('ТРС общая'!$B13=#REF!,ROW(#REF!)-18,""),ROW()-(ROW()-E$2))),"")} | F13: {=IFERROR(INDEX(#REF!,SMALL(IF('ТРС общая'!$B13=#REF!,ROW(#REF!)-18,""),ROW()-(ROW()-F$2))),"")} | G13: {=IFERROR(INDEX(#REF!,SMALL(IF('ТРС общая'!$B13=#REF!,ROW(#REF!)-18,""),ROW()-(ROW()-G$2))),"")} | H13: {=IFERROR(INDEX(#REF!,SMALL(IF('ТРС общая'!$B13=#REF!,ROW(#REF!)-18,""),ROW()-(ROW()-H$2))),"")} | I13: {=IFERROR(INDEX(#REF!,SMALL(IF('ТРС общая'!$B13=#REF!,ROW(#REF!)-18,""),ROW()-(ROW()-I$2))),"")} | J13: {=IFERROR(INDEX(#REF!,SMALL(IF('ТРС общая'!$B13=#REF!,ROW(#REF!)-18,""),ROW()-(ROW()-J$2))),"")} | K13: {=IFERROR(INDEX(#REF!,SMALL(IF('ТРС общая'!$B13=#REF!,ROW(#REF!)-18,""),ROW()-(ROW()-K$2))),"")} | ... AM13: {=IFERROR(INDEX(#REF!,SMALL(IF('ТРС общая'!$B13=#REF!,ROW(#REF!)-18,""),ROW()-(ROW()-AM$2))),"")}
B14: 14 | C14: =COUNTIF('Расчет грейда'!$W:$W,'ТРС общая'!$B14) -> 0 | D14: {=IFERROR(INDEX(#REF!,SMALL(IF('ТРС общая'!$B14=#REF!,ROW(#REF!)-18,""),ROW()-(ROW()-D$2))),"")} | E14: {=IFERROR(INDEX(#REF!,SMALL(IF('ТРС общая'!$B14=#REF!,ROW(#REF!)-18,""),ROW()-(ROW()-E$2))),"")} | F14: {=IFERROR(INDEX(#REF!,SMALL(IF('ТРС общая'!$B14=#REF!,ROW(#REF!)-18,""),ROW()-(ROW()-F$2))),"")} | G14: {=IFERROR(INDEX(#REF!,SMALL(IF('ТРС общая'!$B14=#REF!,ROW(#REF!)-18,""),ROW()-(ROW()-G$2))),"")} | H14: {=IFERROR(INDEX(#REF!,SMALL(IF('ТРС общая'!$B14=#REF!,ROW(#REF!)-18,""),ROW()-(ROW()-H$2))),"")} | I14: {=IFERROR(INDEX(#REF!,SMALL(IF('ТРС общая'!$B14=#REF!,ROW(#REF!)-18,""),ROW()-(ROW()-I$2))),"")} | J14: {=IFERROR(INDEX(#REF!,SMALL(IF('ТРС общая'!$B14=#REF!,ROW(#REF!)-18,""),ROW()-(ROW()-J$2))),"")} | K14: {=IFERROR(INDEX(#REF!,SMALL(IF('ТРС общая'!$B14=#REF!,ROW(#REF!)-18,""),ROW()-(ROW()-K$2))),"")} | ... AM14: {=IFERROR(INDEX(#REF!,SMALL(IF('ТРС общая'!$B14=#REF!,ROW(#REF!)-18,""),ROW()-(ROW()-AM$2))),"")}
B15: 13 | C15: =COUNTIF('Расчет грейда'!$W:$W,'ТРС общая'!$B15) -> 0 | D15: {=IFERROR(INDEX(#REF!,SMALL(IF('ТРС общая'!$B15=#REF!,ROW(#REF!)-18,""),ROW()-(ROW()-D$2))),"")} | E15: {=IFERROR(INDEX(#REF!,SMALL(IF('ТРС общая'!$B15=#REF!,ROW(#REF!)-18,""),ROW()-(ROW()-E$2))),"")} | F15: {=IFERROR(INDEX(#REF!,SMALL(IF('ТРС общая'!$B15=#REF!,ROW(#REF!)-18,""),ROW()-(ROW()-F$2))),"")} | G15: {=IFERROR(INDEX(#REF!,SMALL(IF('ТРС общая'!$B15=#REF!,ROW(#REF!)-18,""),ROW()-(ROW()-G$2))),"")} | H15: {=IFERROR(INDEX(#REF!,SMALL(IF('ТРС общая'!$B15=#REF!,ROW(#REF!)-18,""),ROW()-(ROW()-H$2))),"")} | I15: {=IFERROR(INDEX(#REF!,SMALL(IF('ТРС общая'!$B15=#REF!,ROW(#REF!)-18,""),ROW()-(ROW()-I$2))),"")} | J15: {=IFERROR(INDEX(#REF!,SMALL(IF('ТРС общая'!$B15=#REF!,ROW(#REF!)-18,""),ROW()-(ROW()-J$2))),"")} | K15: {=IFERROR(INDEX(#REF!,SMALL(IF('ТРС общая'!$B15=#REF!,ROW(#REF!)-18,""),ROW()-(ROW()-K$2))),"")} | ... AM15: {=IFERROR(INDEX(#REF!,SMALL(IF('ТРС общая'!$B15=#REF!,ROW(#REF!)-18,""),ROW()-(ROW()-AM$2))),"")}
B16: 12 | C16: =COUNTIF('Расчет грейда'!$W:$W,'ТРС общая'!$B16) -> 0 | D16: {=IFERROR(INDEX(#REF!,SMALL(IF('ТРС общая'!$B16=#REF!,ROW(#REF!)-18,""),ROW()-(ROW()-D$2))),"")} | E16: {=IFERROR(INDEX(#REF!,SMALL(IF('ТРС общая'!$B16=#REF!,ROW(#REF!)-18,""),ROW()-(ROW()-E$2))),"")} | F16: {=IFERROR(INDEX(#REF!,SMALL(IF('ТРС общая'!$B16=#REF!,ROW(#REF!)-18,""),ROW()-(ROW()-F$2))),"")} | G16: {=IFERROR(INDEX(#REF!,SMALL(IF('ТРС общая'!$B16=#REF!,ROW(#REF!)-18,""),ROW()-(ROW()-G$2))),"")} | H16: {=IFERROR(INDEX(#REF!,SMALL(IF('ТРС общая'!$B16=#REF!,ROW(#REF!)-18,""),ROW()-(ROW()-H$2))),"")} | I16: {=IFERROR(INDEX(#REF!,SMALL(IF('ТРС общая'!$B16=#REF!,ROW(#REF!)-18,""),ROW()-(ROW()-I$2))),"")} | J16: {=IFERROR(INDEX(#REF!,SMALL(IF('ТРС общая'!$B16=#REF!,ROW(#REF!)-18,""),ROW()-(ROW()-J$2))),"")} | K16: {=IFERROR(INDEX(#REF!,SMALL(IF('ТРС общая'!$B16=#REF!,ROW(#REF!)-18,""),ROW()-(ROW()-K$2))),"")} | ... AM16: {=IFERROR(INDEX(#REF!,SMALL(IF('ТРС общая'!$B16=#REF!,ROW(#REF!)-18,""),ROW()-(ROW()-AM$2))),"")}
B17: 11 | C17: =COUNTIF('Расчет грейда'!$W:$W,'ТРС общая'!$B17) -> 0 | D17: {=IFERROR(INDEX(#REF!,SMALL(IF('ТРС общая'!$B17=#REF!,ROW(#REF!)-18,""),ROW()-(ROW()-D$2))),"")} | E17: {=IFERROR(INDEX(#REF!,SMALL(IF('ТРС общая'!$B17=#REF!,ROW(#REF!)-18,""),ROW()-(ROW()-E$2))),"")} | F17: {=IFERROR(INDEX(#REF!,SMALL(IF('ТРС общая'!$B17=#REF!,ROW(#REF!)-18,""),ROW()-(ROW()-F$2))),"")} | G17: {=IFERROR(INDEX(#REF!,SMALL(IF('ТРС общая'!$B17=#REF!,ROW(#REF!)-18,""),ROW()-(ROW()-G$2))),"")} | H17: {=IFERROR(INDEX(#REF!,SMALL(IF('ТРС общая'!$B17=#REF!,ROW(#REF!)-18,""),ROW()-(ROW()-H$2))),"")} | I17: {=IFERROR(INDEX(#REF!,SMALL(IF('ТРС общая'!$B17=#REF!,ROW(#REF!)-18,""),ROW()-(ROW()-I$2))),"")} | J17: {=IFERROR(INDEX(#REF!,SMALL(IF('ТРС общая'!$B17=#REF!,ROW(#REF!)-18,""),ROW()-(ROW()-J$2))),"")} | K17: {=IFERROR(INDEX(#REF!,SMALL(IF('ТРС общая'!$B17=#REF!,ROW(#REF!)-18,""),ROW()-(ROW()-K$2))),"")} | ... AM17: {=IFERROR(INDEX(#REF!,SMALL(IF('ТРС общая'!$B17=#REF!,ROW(#REF!)-18,""),ROW()-(ROW()-AM$2))),"")}
B18: 10 | C18: =COUNTIF('Расчет грейда'!$W:$W,'ТРС общая'!$B18) -> 0 | D18: {=IFERROR(INDEX(#REF!,SMALL(IF('ТРС общая'!$B18=#REF!,ROW(#REF!)-18,""),ROW()-(ROW()-D$2))),"")} | E18: {=IFERROR(INDEX(#REF!,SMALL(IF('ТРС общая'!$B18=#REF!,ROW(#REF!)-18,""),ROW()-(ROW()-E$2))),"")} | F18: {=IFERROR(INDEX(#REF!,SMALL(IF('ТРС общая'!$B18=#REF!,ROW(#REF!)-18,""),ROW()-(ROW()-F$2))),"")} | G18: {=IFERROR(INDEX(#REF!,SMALL(IF('ТРС общая'!$B18=#REF!,ROW(#REF!)-18,""),ROW()-(ROW()-G$2))),"")} | H18: {=IFERROR(INDEX(#REF!,SMALL(IF('ТРС общая'!$B18=#REF!,ROW(#REF!)-18,""),ROW()-(ROW()-H$2))),"")} | I18: {=IFERROR(INDEX(#REF!,SMALL(IF('ТРС общая'!$B18=#REF!,ROW(#REF!)-18,""),ROW()-(ROW()-I$2))),"")} | J18: {=IFERROR(INDEX(#REF!,SMALL(IF('ТРС общая'!$B18=#REF!,ROW(#REF!)-18,""),ROW()-(ROW()-J$2))),"")} | K18: {=IFERROR(INDEX(#REF!,SMALL(IF('ТРС общая'!$B18=#REF!,ROW(#REF!)-18,""),ROW()-(ROW()-K$2))),"")} | ... AM18: {=IFERROR(INDEX(#REF!,SMALL(IF('ТРС общая'!$B18=#REF!,ROW(#REF!)-18,""),ROW()-(ROW()-AM$2))),"")}
B19: 9 | C19: =COUNTIF('Расчет грейда'!$W:$W,'ТРС общая'!$B19) -> 0 | D19: {=IFERROR(INDEX(#REF!,SMALL(IF('ТРС общая'!$B19=#REF!,ROW(#REF!)-18,""),ROW()-(ROW()-D$2))),"")} | E19: {=IFERROR(INDEX(#REF!,SMALL(IF('ТРС общая'!$B19=#REF!,ROW(#REF!)-18,""),ROW()-(ROW()-E$2))),"")} | F19: {=IFERROR(INDEX(#REF!,SMALL(IF('ТРС общая'!$B19=#REF!,ROW(#REF!)-18,""),ROW()-(ROW()-F$2))),"")} | G19: {=IFERROR(INDEX(#REF!,SMALL(IF('ТРС общая'!$B19=#REF!,ROW(#REF!)-18,""),ROW()-(ROW()-G$2))),"")} | H19: {=IFERROR(INDEX(#REF!,SMALL(IF('ТРС общая'!$B19=#REF!,ROW(#REF!)-18,""),ROW()-(ROW()-H$2))),"")} | I19: {=IFERROR(INDEX(#REF!,SMALL(IF('ТРС общая'!$B19=#REF!,ROW(#REF!)-18,""),ROW()-(ROW()-I$2))),"")} | J19: {=IFERROR(INDEX(#REF!,SMALL(IF('ТРС общая'!$B19=#REF!,ROW(#REF!)-18,""),ROW()-(ROW()-J$2))),"")} | K19: {=IFERROR(INDEX(#REF!,SMALL(IF('ТРС общая'!$B19=#REF!,ROW(#REF!)-18,""),ROW()-(ROW()-K$2))),"")} | ... AM19: {=IFERROR(INDEX(#REF!,SMALL(IF('ТРС общая'!$B19=#REF!,ROW(#REF!)-18,""),ROW()-(ROW()-AM$2))),"")}
... B28: 0 | C28: =COUNTIF('Расчет грейда'!$W:$W,'ТРС общая'!$B28) -> 0 | D28: {=IFERROR(INDEX(#REF!,SMALL(IF('ТРС общая'!$B28=#REF!,ROW(#REF!)-18,""),ROW()-(ROW()-D$2))),"")} | E28: {=IFERROR(INDEX(#REF!,SMALL(IF('ТРС общая'!$B28=#REF!,ROW(#REF!)-18,""),ROW()-(ROW()-E$2))),"")} | F28: {=IFERROR(INDEX(#REF!,SMALL(IF('ТРС общая'!$B28=#REF!,ROW(#REF!)-18,""),ROW()-(ROW()-F$2))),"")} | G28: {=IFERROR(INDEX(#REF!,SMALL(IF('ТРС общая'!$B28=#REF!,ROW(#REF!)-18,""),ROW()-(ROW()-G$2))),"")} | H28: {=IFERROR(INDEX(#REF!,SMALL(IF('ТРС общая'!$B28=#REF!,ROW(#REF!)-18,""),ROW()-(ROW()-H$2))),"")} | I28: {=IFERROR(INDEX(#REF!,SMALL(IF('ТРС общая'!$B28=#REF!,ROW(#REF!)-18,""),ROW()-(ROW()-I$2))),"")} | J28: {=IFERROR(INDEX(#REF!,SMALL(IF('ТРС общая'!$B28=#REF!,ROW(#REF!)-18,""),ROW()-(ROW()-J$2))),"")} | K28: {=IFERROR(INDEX(#REF!,SMALL(IF('ТРС общая'!$B28=#REF!,ROW(#REF!)-18,""),ROW()-(ROW()-K$2))),"")} | ... AM28: {=IFERROR(INDEX(#REF!,SMALL(IF('ТРС общая'!$B28=#REF!,ROW(#REF!)-18,""),ROW()-(ROW()-AM$2))),"")}
B39: TO BE
B40: Грейд | C40: Кол-во ролей
B41: 20 | C41: =COUNTIF('Расчет грейда'!$W:$W,'ТРС общая'!$B41) -> 0 | D41: {=IFERROR(INDEX('Расчет грейда'!$I$19:$I$200,SMALL(IF('ТРС общая'!$B41='Расчет грейда'!$W$19:$W$200,ROW('Расчет грейда'!$I$19:$I$200)-18,""),ROW()-(ROW()-D$2))),"")} | E41: {=IFERROR(INDEX('Расчет грейда'!$I$19:$I$200,SMALL(IF('ТРС общая'!$B41='Расчет грейда'!$W$19:$W$200,ROW('Расчет грейда'!$I$19:$I$200)-18,""),ROW()-(ROW()-E$2))),"")} | F41: {=IFERROR(INDEX('Расчет грейда'!$I$19:$I$200,SMALL(IF('ТРС общая'!$B41='Расчет грейда'!$W$19:$W$200,ROW('Расчет грейда'!$I$19:$I$200)-18,""),ROW()-(ROW()-F$2))),"")} | G41: {=IFERROR(INDEX('Расчет грейда'!$I$19:$I$200,SMALL(IF('ТРС общая'!$B41='Расчет грейда'!$W$19:$W$200,ROW('Расчет грейда'!$I$19:$I$200)-18,""),ROW()-(ROW()-G$2))),"")} | H41: {=IFERROR(INDEX('Расчет грейда'!$I$19:$I$200,SMALL(IF('ТРС общая'!$B41='Расчет грейда'!$W$19:$W$200,ROW('Расчет грейда'!$I$19:$I$200)-18,""),ROW()-(ROW()-H$2))),"")} | I41: {=IFERROR(INDEX('Расчет грейда'!$I$19:$I$200,SMALL(IF('ТРС общая'!$B41='Расчет грейда'!$W$19:$W$200,ROW('Расчет грейда'!$I$19:$I$200)-18,""),ROW()-(ROW()-I$2))),"")} | J41: {=IFERROR(INDEX('Расчет грейда'!$I$19:$I$200,SMALL(IF('ТРС общая'!$B41='Расчет грейда'!$W$19:$W$200,ROW('Расчет грейда'!$I$19:$I$200)-18,""),ROW()-(ROW()-J$2))),"")} | K41: {=IFERROR(INDEX('Расчет грейда'!$I$19:$I$200,SMALL(IF('ТРС общая'!$B41='Расчет грейда'!$W$19:$W$200,ROW('Расчет грейда'!$I$19:$I$200)-18,""),ROW()-(ROW()-K$2))),"")} | ... AO41: {=IFERROR(INDEX('Расчет грейда'!$I$19:$I$200,SMALL(IF('ТРС общая'!$B41='Расчет грейда'!$W$19:$W$200,ROW('Расчет грейда'!$I$19:$I$200)-18,""),ROW()-(ROW()-AO$2))),"")}
B42: 19 | C42: =COUNTIF('Расчет грейда'!$W:$W,'ТРС общая'!$B42) -> 0 | D42: {=IFERROR(INDEX('Расчет грейда'!$I$19:$I$200,SMALL(IF('ТРС общая'!$B42='Расчет грейда'!$W$19:$W$200,ROW('Расчет грейда'!$I$19:$I$200)-18,""),ROW()-(ROW()-D$2))),"")} | E42: {=IFERROR(INDEX('Расчет грейда'!$I$19:$I$200,SMALL(IF('ТРС общая'!$B42='Расчет грейда'!$W$19:$W$200,ROW('Расчет грейда'!$I$19:$I$200)-18,""),ROW()-(ROW()-E$2))),"")} | F42: {=IFERROR(INDEX('Расчет грейда'!$I$19:$I$200,SMALL(IF('ТРС общая'!$B42='Расчет грейда'!$W$19:$W$200,ROW('Расчет грейда'!$I$19:$I$200)-18,""),ROW()-(ROW()-F$2))),"")} | G42: {=IFERROR(INDEX('Расчет грейда'!$I$19:$I$200,SMALL(IF('ТРС общая'!$B42='Расчет грейда'!$W$19:$W$200,ROW('Расчет грейда'!$I$19:$I$200)-18,""),ROW()-(ROW()-G$2))),"")} | H42: {=IFERROR(INDEX('Расчет грейда'!$I$19:$I$200,SMALL(IF('ТРС общая'!$B42='Расчет грейда'!$W$19:$W$200,ROW('Расчет грейда'!$I$19:$I$200)-18,""),ROW()-(ROW()-H$2))),"")} | I42: {=IFERROR(INDEX('Расчет грейда'!$I$19:$I$200,SMALL(IF('ТРС общая'!$B42='Расчет грейда'!$W$19:$W$200,ROW('Расчет грейда'!$I$19:$I$200)-18,""),ROW()-(ROW()-I$2))),"")} | J42: {=IFERROR(INDEX('Расчет грейда'!$I$19:$I$200,SMALL(IF('ТРС общая'!$B42='Расчет грейда'!$W$19:$W$200,ROW('Расчет грейда'!$I$19:$I$200)-18,""),ROW()-(ROW()-J$2))),"")} | K42: {=IFERROR(INDEX('Расчет грейда'!$I$19:$I$200,SMALL(IF('ТРС общая'!$B42='Расчет грейда'!$W$19:$W$200,ROW('Расчет грейда'!$I$19:$I$200)-18,""),ROW()-(ROW()-K$2))),"")} | ... AO42: {=IFERROR(INDEX('Расчет грейда'!$I$19:$I$200,SMALL(IF('ТРС общая'!$B42='Расчет грейда'!$W$19:$W$200,ROW('Расчет грейда'!$I$19:$I$200)-18,""),ROW()-(ROW()-AO$2))),"")}
B43: 18 | C43: =COUNTIF('Расчет грейда'!$W:$W,'ТРС общая'!$B43) -> 0 | D43: {=IFERROR(INDEX('Расчет грейда'!$I$19:$I$200,SMALL(IF('ТРС общая'!$B43='Расчет грейда'!$W$19:$W$200,ROW('Расчет грейда'!$I$19:$I$200)-18,""),ROW()-(ROW()-D$2))),"")} | E43: {=IFERROR(INDEX('Расчет грейда'!$I$19:$I$200,SMALL(IF('ТРС общая'!$B43='Расчет грейда'!$W$19:$W$200,ROW('Расчет грейда'!$I$19:$I$200)-18,""),ROW()-(ROW()-E$2))),"")} | F43: {=IFERROR(INDEX('Расчет грейда'!$I$19:$I$200,SMALL(IF('ТРС общая'!$B43='Расчет грейда'!$W$19:$W$200,ROW('Расчет грейда'!$I$19:$I$200)-18,""),ROW()-(ROW()-F$2))),"")} | G43: {=IFERROR(INDEX('Расчет грейда'!$I$19:$I$200,SMALL(IF('ТРС общая'!$B43='Расчет грейда'!$W$19:$W$200,ROW('Расчет грейда'!$I$19:$I$200)-18,""),ROW()-(ROW()-G$2))),"")} | H43: {=IFERROR(INDEX('Расчет грейда'!$I$19:$I$200,SMALL(IF('ТРС общая'!$B43='Расчет грейда'!$W$19:$W$200,ROW('Расчет грейда'!$I$19:$I$200)-18,""),ROW()-(ROW()-H$2))),"")} | I43: {=IFERROR(INDEX('Расчет грейда'!$I$19:$I$200,SMALL(IF('ТРС общая'!$B43='Расчет грейда'!$W$19:$W$200,ROW('Расчет грейда'!$I$19:$I$200)-18,""),ROW()-(ROW()-I$2))),"")} | J43: {=IFERROR(INDEX('Расчет грейда'!$I$19:$I$200,SMALL(IF('ТРС общая'!$B43='Расчет грейда'!$W$19:$W$200,ROW('Расчет грейда'!$I$19:$I$200)-18,""),ROW()-(ROW()-J$2))),"")} | K43: {=IFERROR(INDEX('Расчет грейда'!$I$19:$I$200,SMALL(IF('ТРС общая'!$B43='Расчет грейда'!$W$19:$W$200,ROW('Расчет грейда'!$I$19:$I$200)-18,""),ROW()-(ROW()-K$2))),"")} | ... AO43: {=IFERROR(INDEX('Расчет грейда'!$I$19:$I$200,SMALL(IF('ТРС общая'!$B43='Расчет грейда'!$W$19:$W$200,ROW('Расчет грейда'!$I$19:$I$200)-18,""),ROW()-(ROW()-AO$2))),"")}
B44: 17 | C44: =COUNTIF('Расчет грейда'!$W:$W,'ТРС общая'!$B44) -> 0 | D44: {=IFERROR(INDEX('Расчет грейда'!$I$19:$I$200,SMALL(IF('ТРС общая'!$B44='Расчет грейда'!$W$19:$W$200,ROW('Расчет грейда'!$I$19:$I$200)-18,""),ROW()-(ROW()-D$2))),"")} | E44: {=IFERROR(INDEX('Расчет грейда'!$I$19:$I$200,SMALL(IF('ТРС общая'!$B44='Расчет грейда'!$W$19:$W$200,ROW('Расчет грейда'!$I$19:$I$200)-18,""),ROW()-(ROW()-E$2))),"")} | F44: {=IFERROR(INDEX('Расчет грейда'!$I$19:$I$200,SMALL(IF('ТРС общая'!$B44='Расчет грейда'!$W$19:$W$200,ROW('Расчет грейда'!$I$19:$I$200)-18,""),ROW()-(ROW()-F$2))),"")} | G44: {=IFERROR(INDEX('Расчет грейда'!$I$19:$I$200,SMALL(IF('ТРС общая'!$B44='Расчет грейда'!$W$19:$W$200,ROW('Расчет грейда'!$I$19:$I$200)-18,""),ROW()-(ROW()-G$2))),"")} | H44: {=IFERROR(INDEX('Расчет грейда'!$I$19:$I$200,SMALL(IF('ТРС общая'!$B44='Расчет грейда'!$W$19:$W$200,ROW('Расчет грейда'!$I$19:$I$200)-18,""),ROW()-(ROW()-H$2))),"")} | I44: {=IFERROR(INDEX('Расчет грейда'!$I$19:$I$200,SMALL(IF('ТРС общая'!$B44='Расчет грейда'!$W$19:$W$200,ROW('Расчет грейда'!$I$19:$I$200)-18,""),ROW()-(ROW()-I$2))),"")} | J44: {=IFERROR(INDEX('Расчет грейда'!$I$19:$I$200,SMALL(IF('ТРС общая'!$B44='Расчет грейда'!$W$19:$W$200,ROW('Расчет грейда'!$I$19:$I$200)-18,""),ROW()-(ROW()-J$2))),"")} | K44: {=IFERROR(INDEX('Расчет грейда'!$I$19:$I$200,SMALL(IF('ТРС общая'!$B44='Расчет грейда'!$W$19:$W$200,ROW('Расчет грейда'!$I$19:$I$200)-18,""),ROW()-(ROW()-K$2))),"")} | ... AO44: {=IFERROR(INDEX('Расчет грейда'!$I$19:$I$200,SMALL(IF('ТРС общая'!$B44='Расчет грейда'!$W$19:$W$200,ROW('Расчет грейда'!$I$19:$I$200)-18,""),ROW()-(ROW()-AO$2))),"")}
B45: 16 | C45: =COUNTIF('Расчет грейда'!$W:$W,'ТРС общая'!$B45) -> 0 | D45: {=IFERROR(INDEX('Расчет грейда'!$I$19:$I$200,SMALL(IF('ТРС общая'!$B45='Расчет грейда'!$W$19:$W$200,ROW('Расчет грейда'!$I$19:$I$200)-18,""),ROW()-(ROW()-D$2))),"")} | E45: {=IFERROR(INDEX('Расчет грейда'!$I$19:$I$200,SMALL(IF('ТРС общая'!$B45='Расчет грейда'!$W$19:$W$200,ROW('Расчет грейда'!$I$19:$I$200)-18,""),ROW()-(ROW()-E$2))),"")} | F45: {=IFERROR(INDEX('Расчет грейда'!$I$19:$I$200,SMALL(IF('ТРС общая'!$B45='Расчет грейда'!$W$19:$W$200,ROW('Расчет грейда'!$I$19:$I$200)-18,""),ROW()-(ROW()-F$2))),"")} | G45: {=IFERROR(INDEX('Расчет грейда'!$I$19:$I$200,SMALL(IF('ТРС общая'!$B45='Расчет грейда'!$W$19:$W$200,ROW('Расчет грейда'!$I$19:$I$200)-18,""),ROW()-(ROW()-G$2))),"")} | H45: {=IFERROR(INDEX('Расчет грейда'!$I$19:$I$200,SMALL(IF('ТРС общая'!$B45='Расчет грейда'!$W$19:$W$200,ROW('Расчет грейда'!$I$19:$I$200)-18,""),ROW()-(ROW()-H$2))),"")} | I45: {=IFERROR(INDEX('Расчет грейда'!$I$19:$I$200,SMALL(IF('ТРС общая'!$B45='Расчет грейда'!$W$19:$W$200,ROW('Расчет грейда'!$I$19:$I$200)-18,""),ROW()-(ROW()-I$2))),"")} | J45: {=IFERROR(INDEX('Расчет грейда'!$I$19:$I$200,SMALL(IF('ТРС общая'!$B45='Расчет грейда'!$W$19:$W$200,ROW('Расчет грейда'!$I$19:$I$200)-18,""),ROW()-(ROW()-J$2))),"")} | K45: {=IFERROR(INDEX('Расчет грейда'!$I$19:$I$200,SMALL(IF('ТРС общая'!$B45='Расчет грейда'!$W$19:$W$200,ROW('Расчет грейда'!$I$19:$I$200)-18,""),ROW()-(ROW()-K$2))),"")} | ... AO45: {=IFERROR(INDEX('Расчет грейда'!$I$19:$I$200,SMALL(IF('ТРС общая'!$B45='Расчет грейда'!$W$19:$W$200,ROW('Расчет грейда'!$I$19:$I$200)-18,""),ROW()-(ROW()-AO$2))),"")}
B46: 15 | C46: =COUNTIF('Расчет грейда'!$W:$W,'ТРС общая'!$B46) -> 0 | D46: {=IFERROR(INDEX('Расчет грейда'!$I$19:$I$200,SMALL(IF('ТРС общая'!$B46='Расчет грейда'!$W$19:$W$200,ROW('Расчет грейда'!$I$19:$I$200)-18,""),ROW()-(ROW()-D$2))),"")} | E46: {=IFERROR(INDEX('Расчет грейда'!$I$19:$I$200,SMALL(IF('ТРС общая'!$B46='Расчет грейда'!$W$19:$W$200,ROW('Расчет грейда'!$I$19:$I$200)-18,""),ROW()-(ROW()-E$2))),"")} | F46: {=IFERROR(INDEX('Расчет грейда'!$I$19:$I$200,SMALL(IF('ТРС общая'!$B46='Расчет грейда'!$W$19:$W$200,ROW('Расчет грейда'!$I$19:$I$200)-18,""),ROW()-(ROW()-F$2))),"")} | G46: {=IFERROR(INDEX('Расчет грейда'!$I$19:$I$200,SMALL(IF('ТРС общая'!$B46='Расчет грейда'!$W$19:$W$200,ROW('Расчет грейда'!$I$19:$I$200)-18,""),ROW()-(ROW()-G$2))),"")} | H46: {=IFERROR(INDEX('Расчет грейда'!$I$19:$I$200,SMALL(IF('ТРС общая'!$B46='Расчет грейда'!$W$19:$W$200,ROW('Расчет грейда'!$I$19:$I$200)-18,""),ROW()-(ROW()-H$2))),"")} | I46: {=IFERROR(INDEX('Расчет грейда'!$I$19:$I$200,SMALL(IF('ТРС общая'!$B46='Расчет грейда'!$W$19:$W$200,ROW('Расчет грейда'!$I$19:$I$200)-18,""),ROW()-(ROW()-I$2))),"")} | J46: {=IFERROR(INDEX('Расчет грейда'!$I$19:$I$200,SMALL(IF('ТРС общая'!$B46='Расчет грейда'!$W$19:$W$200,ROW('Расчет грейда'!$I$19:$I$200)-18,""),ROW()-(ROW()-J$2))),"")} | K46: {=IFERROR(INDEX('Расчет грейда'!$I$19:$I$200,SMALL(IF('ТРС общая'!$B46='Расчет грейда'!$W$19:$W$200,ROW('Расчет грейда'!$I$19:$I$200)-18,""),ROW()-(ROW()-K$2))),"")} | ... AO46: {=IFERROR(INDEX('Расчет грейда'!$I$19:$I$200,SMALL(IF('ТРС общая'!$B46='Расчет грейда'!$W$19:$W$200,ROW('Расчет грейда'!$I$19:$I$200)-18,""),ROW()-(ROW()-AO$2))),"")}
B47: 14 | C47: =COUNTIF('Расчет грейда'!$W:$W,'ТРС общая'!$B47) -> 0 | D47: {=IFERROR(INDEX('Расчет грейда'!$I$19:$I$200,SMALL(IF('ТРС общая'!$B47='Расчет грейда'!$W$19:$W$200,ROW('Расчет грейда'!$I$19:$I$200)-18,""),ROW()-(ROW()-D$2))),"")} | E47: {=IFERROR(INDEX('Расчет грейда'!$I$19:$I$200,SMALL(IF('ТРС общая'!$B47='Расчет грейда'!$W$19:$W$200,ROW('Расчет грейда'!$I$19:$I$200)-18,""),ROW()-(ROW()-E$2))),"")} | F47: {=IFERROR(INDEX('Расчет грейда'!$I$19:$I$200,SMALL(IF('ТРС общая'!$B47='Расчет грейда'!$W$19:$W$200,ROW('Расчет грейда'!$I$19:$I$200)-18,""),ROW()-(ROW()-F$2))),"")} | G47: {=IFERROR(INDEX('Расчет грейда'!$I$19:$I$200,SMALL(IF('ТРС общая'!$B47='Расчет грейда'!$W$19:$W$200,ROW('Расчет грейда'!$I$19:$I$200)-18,""),ROW()-(ROW()-G$2))),"")} | H47: {=IFERROR(INDEX('Расчет грейда'!$I$19:$I$200,SMALL(IF('ТРС общая'!$B47='Расчет грейда'!$W$19:$W$200,ROW('Расчет грейда'!$I$19:$I$200)-18,""),ROW()-(ROW()-H$2))),"")} | I47: {=IFERROR(INDEX('Расчет грейда'!$I$19:$I$200,SMALL(IF('ТРС общая'!$B47='Расчет грейда'!$W$19:$W$200,ROW('Расчет грейда'!$I$19:$I$200)-18,""),ROW()-(ROW()-I$2))),"")} | J47: {=IFERROR(INDEX('Расчет грейда'!$I$19:$I$200,SMALL(IF('ТРС общая'!$B47='Расчет грейда'!$W$19:$W$200,ROW('Расчет грейда'!$I$19:$I$200)-18,""),ROW()-(ROW()-J$2))),"")} | K47: {=IFERROR(INDEX('Расчет грейда'!$I$19:$I$200,SMALL(IF('ТРС общая'!$B47='Расчет грейда'!$W$19:$W$200,ROW('Расчет грейда'!$I$19:$I$200)-18,""),ROW()-(ROW()-K$2))),"")} | ... AO47: {=IFERROR(INDEX('Расчет грейда'!$I$19:$I$200,SMALL(IF('ТРС общая'!$B47='Расчет грейда'!$W$19:$W$200,ROW('Расчет грейда'!$I$19:$I$200)-18,""),ROW()-(ROW()-AO$2))),"")}
B48: 13 | C48: =COUNTIF('Расчет грейда'!$W:$W,'ТРС общая'!$B48) -> 0 | D48: {=IFERROR(INDEX('Расчет грейда'!$I$19:$I$200,SMALL(IF('ТРС общая'!$B48='Расчет грейда'!$W$19:$W$200,ROW('Расчет грейда'!$I$19:$I$200)-18,""),ROW()-(ROW()-D$2))),"")} | E48: {=IFERROR(INDEX('Расчет грейда'!$I$19:$I$200,SMALL(IF('ТРС общая'!$B48='Расчет грейда'!$W$19:$W$200,ROW('Расчет грейда'!$I$19:$I$200)-18,""),ROW()-(ROW()-E$2))),"")} | F48: {=IFERROR(INDEX('Расчет грейда'!$I$19:$I$200,SMALL(IF('ТРС общая'!$B48='Расчет грейда'!$W$19:$W$200,ROW('Расчет грейда'!$I$19:$I$200)-18,""),ROW()-(ROW()-F$2))),"")} | G48: {=IFERROR(INDEX('Расчет грейда'!$I$19:$I$200,SMALL(IF('ТРС общая'!$B48='Расчет грейда'!$W$19:$W$200,ROW('Расчет грейда'!$I$19:$I$200)-18,""),ROW()-(ROW()-G$2))),"")} | H48: {=IFERROR(INDEX('Расчет грейда'!$I$19:$I$200,SMALL(IF('ТРС общая'!$B48='Расчет грейда'!$W$19:$W$200,ROW('Расчет грейда'!$I$19:$I$200)-18,""),ROW()-(ROW()-H$2))),"")} | I48: {=IFERROR(INDEX('Расчет грейда'!$I$19:$I$200,SMALL(IF('ТРС общая'!$B48='Расчет грейда'!$W$19:$W$200,ROW('Расчет грейда'!$I$19:$I$200)-18,""),ROW()-(ROW()-I$2))),"")} | J48: {=IFERROR(INDEX('Расчет грейда'!$I$19:$I$200,SMALL(IF('ТРС общая'!$B48='Расчет грейда'!$W$19:$W$200,ROW('Расчет грейда'!$I$19:$I$200)-18,""),ROW()-(ROW()-J$2))),"")} | K48: {=IFERROR(INDEX('Расчет грейда'!$I$19:$I$200,SMALL(IF('ТРС общая'!$B48='Расчет грейда'!$W$19:$W$200,ROW('Расчет грейда'!$I$19:$I$200)-18,""),ROW()-(ROW()-K$2))),"")} | ... AO48: {=IFERROR(INDEX('Расчет грейда'!$I$19:$I$200,SMALL(IF('ТРС общая'!$B48='Расчет грейда'!$W$19:$W$200,ROW('Расчет грейда'!$I$19:$I$200)-18,""),ROW()-(ROW()-AO$2))),"")}
B49: 12 | C49: =COUNTIF('Расчет грейда'!$W:$W,'ТРС общая'!$B49) -> 0 | D49: {=IFERROR(INDEX('Расчет грейда'!$I$19:$I$200,SMALL(IF('ТРС общая'!$B49='Расчет грейда'!$W$19:$W$200,ROW('Расчет грейда'!$I$19:$I$200)-18,""),ROW()-(ROW()-D$2))),"")} | E49: {=IFERROR(INDEX('Расчет грейда'!$I$19:$I$200,SMALL(IF('ТРС общая'!$B49='Расчет грейда'!$W$19:$W$200,ROW('Расчет грейда'!$I$19:$I$200)-18,""),ROW()-(ROW()-E$2))),"")} | F49: {=IFERROR(INDEX('Расчет грейда'!$I$19:$I$200,SMALL(IF('ТРС общая'!$B49='Расчет грейда'!$W$19:$W$200,ROW('Расчет грейда'!$I$19:$I$200)-18,""),ROW()-(ROW()-F$2))),"")} | G49: {=IFERROR(INDEX('Расчет грейда'!$I$19:$I$200,SMALL(IF('ТРС общая'!$B49='Расчет грейда'!$W$19:$W$200,ROW('Расчет грейда'!$I$19:$I$200)-18,""),ROW()-(ROW()-G$2))),"")} | H49: {=IFERROR(INDEX('Расчет грейда'!$I$19:$I$200,SMALL(IF('ТРС общая'!$B49='Расчет грейда'!$W$19:$W$200,ROW('Расчет грейда'!$I$19:$I$200)-18,""),ROW()-(ROW()-H$2))),"")} | I49: {=IFERROR(INDEX('Расчет грейда'!$I$19:$I$200,SMALL(IF('ТРС общая'!$B49='Расчет грейда'!$W$19:$W$200,ROW('Расчет грейда'!$I$19:$I$200)-18,""),ROW()-(ROW()-I$2))),"")} | J49: {=IFERROR(INDEX('Расчет грейда'!$I$19:$I$200,SMALL(IF('ТРС общая'!$B49='Расчет грейда'!$W$19:$W$200,ROW('Расчет грейда'!$I$19:$I$200)-18,""),ROW()-(ROW()-J$2))),"")} | K49: {=IFERROR(INDEX('Расчет грейда'!$I$19:$I$200,SMALL(IF('ТРС общая'!$B49='Расчет грейда'!$W$19:$W$200,ROW('Расчет грейда'!$I$19:$I$200)-18,""),ROW()-(ROW()-K$2))),"")} | ... AO49: {=IFERROR(INDEX('Расчет грейда'!$I$19:$I$200,SMALL(IF('ТРС общая'!$B49='Расчет грейда'!$W$19:$W$200,ROW('Расчет грейда'!$I$19:$I$200)-18,""),ROW()-(ROW()-AO$2))),"")}
B50: 11 | C50: =COUNTIF('Расчет грейда'!$W:$W,'ТРС общая'!$B50) -> 0 | D50: {=IFERROR(INDEX('Расчет грейда'!$I$19:$I$200,SMALL(IF('ТРС общая'!$B50='Расчет грейда'!$W$19:$W$200,ROW('Расчет грейда'!$I$19:$I$200)-18,""),ROW()-(ROW()-D$2))),"")} | E50: {=IFERROR(INDEX('Расчет грейда'!$I$19:$I$200,SMALL(IF('ТРС общая'!$B50='Расчет грейда'!$W$19:$W$200,ROW('Расчет грейда'!$I$19:$I$200)-18,""),ROW()-(ROW()-E$2))),"")} | F50: {=IFERROR(INDEX('Расчет грейда'!$I$19:$I$200,SMALL(IF('ТРС общая'!$B50='Расчет грейда'!$W$19:$W$200,ROW('Расчет грейда'!$I$19:$I$200)-18,""),ROW()-(ROW()-F$2))),"")} | G50: {=IFERROR(INDEX('Расчет грейда'!$I$19:$I$200,SMALL(IF('ТРС общая'!$B50='Расчет грейда'!$W$19:$W$200,ROW('Расчет грейда'!$I$19:$I$200)-18,""),ROW()-(ROW()-G$2))),"")} | H50: {=IFERROR(INDEX('Расчет грейда'!$I$19:$I$200,SMALL(IF('ТРС общая'!$B50='Расчет грейда'!$W$19:$W$200,ROW('Расчет грейда'!$I$19:$I$200)-18,""),ROW()-(ROW()-H$2))),"")} | I50: {=IFERROR(INDEX('Расчет грейда'!$I$19:$I$200,SMALL(IF('ТРС общая'!$B50='Расчет грейда'!$W$19:$W$200,ROW('Расчет грейда'!$I$19:$I$200)-18,""),ROW()-(ROW()-I$2))),"")} | J50: {=IFERROR(INDEX('Расчет грейда'!$I$19:$I$200,SMALL(IF('ТРС общая'!$B50='Расчет грейда'!$W$19:$W$200,ROW('Расчет грейда'!$I$19:$I$200)-18,""),ROW()-(ROW()-J$2))),"")} | K50: {=IFERROR(INDEX('Расчет грейда'!$I$19:$I$200,SMALL(IF('ТРС общая'!$B50='Расчет грейда'!$W$19:$W$200,ROW('Расчет грейда'!$I$19:$I$200)-18,""),ROW()-(ROW()-K$2))),"")} | ... AO50: {=IFERROR(INDEX('Расчет грейда'!$I$19:$I$200,SMALL(IF('ТРС общая'!$B50='Расчет грейда'!$W$19:$W$200,ROW('Расчет грейда'!$I$19:$I$200)-18,""),ROW()-(ROW()-AO$2))),"")}
B51: 10 | C51: =COUNTIF('Расчет грейда'!$W:$W,'ТРС общая'!$B51) -> 0 | D51: {=IFERROR(INDEX('Расчет грейда'!$I$19:$I$200,SMALL(IF('ТРС общая'!$B51='Расчет грейда'!$W$19:$W$200,ROW('Расчет грейда'!$I$19:$I$200)-18,""),ROW()-(ROW()-D$2))),"")} | E51: {=IFERROR(INDEX('Расчет грейда'!$I$19:$I$200,SMALL(IF('ТРС общая'!$B51='Расчет грейда'!$W$19:$W$200,ROW('Расчет грейда'!$I$19:$I$200)-18,""),ROW()-(ROW()-E$2))),"")} | F51: {=IFERROR(INDEX('Расчет грейда'!$I$19:$I$200,SMALL(IF('ТРС общая'!$B51='Расчет грейда'!$W$19:$W$200,ROW('Расчет грейда'!$I$19:$I$200)-18,""),ROW()-(ROW()-F$2))),"")} | G51: {=IFERROR(INDEX('Расчет грейда'!$I$19:$I$200,SMALL(IF('ТРС общая'!$B51='Расчет грейда'!$W$19:$W$200,ROW('Расчет грейда'!$I$19:$I$200)-18,""),ROW()-(ROW()-G$2))),"")} | H51: {=IFERROR(INDEX('Расчет грейда'!$I$19:$I$200,SMALL(IF('ТРС общая'!$B51='Расчет грейда'!$W$19:$W$200,ROW('Расчет грейда'!$I$19:$I$200)-18,""),ROW()-(ROW()-H$2))),"")} | I51: {=IFERROR(INDEX('Расчет грейда'!$I$19:$I$200,SMALL(IF('ТРС общая'!$B51='Расчет грейда'!$W$19:$W$200,ROW('Расчет грейда'!$I$19:$I$200)-18,""),ROW()-(ROW()-I$2))),"")} | J51: {=IFERROR(INDEX('Расчет грейда'!$I$19:$I$200,SMALL(IF('ТРС общая'!$B51='Расчет грейда'!$W$19:$W$200,ROW('Расчет грейда'!$I$19:$I$200)-18,""),ROW()-(ROW()-J$2))),"")} | K51: {=IFERROR(INDEX('Расчет грейда'!$I$19:$I$200,SMALL(IF('ТРС общая'!$B51='Расчет грейда'!$W$19:$W$200,ROW('Расчет грейда'!$I$19:$I$200)-18,""),ROW()-(ROW()-K$2))),"")} | ... AO51: {=IFERROR(INDEX('Расчет грейда'!$I$19:$I$200,SMALL(IF('ТРС общая'!$B51='Расчет грейда'!$W$19:$W$200,ROW('Расчет грейда'!$I$19:$I$200)-18,""),ROW()-(ROW()-AO$2))),"")}
B52: 9 | C52: =COUNTIF('Расчет грейда'!$W:$W,'ТРС общая'!$B52) -> 0 | D52: {=IFERROR(INDEX('Расчет грейда'!$I$19:$I$200,SMALL(IF('ТРС общая'!$B52='Расчет грейда'!$W$19:$W$200,ROW('Расчет грейда'!$I$19:$I$200)-18,""),ROW()-(ROW()-D$2))),"")} | E52: {=IFERROR(INDEX('Расчет грейда'!$I$19:$I$200,SMALL(IF('ТРС общая'!$B52='Расчет грейда'!$W$19:$W$200,ROW('Расчет грейда'!$I$19:$I$200)-18,""),ROW()-(ROW()-E$2))),"")} | F52: {=IFERROR(INDEX('Расчет грейда'!$I$19:$I$200,SMALL(IF('ТРС общая'!$B52='Расчет грейда'!$W$19:$W$200,ROW('Расчет грейда'!$I$19:$I$200)-18,""),ROW()-(ROW()-F$2))),"")} | G52: {=IFERROR(INDEX('Расчет грейда'!$I$19:$I$200,SMALL(IF('ТРС общая'!$B52='Расчет грейда'!$W$19:$W$200,ROW('Расчет грейда'!$I$19:$I$200)-18,""),ROW()-(ROW()-G$2))),"")} | H52: {=IFERROR(INDEX('Расчет грейда'!$I$19:$I$200,SMALL(IF('ТРС общая'!$B52='Расчет грейда'!$W$19:$W$200,ROW('Расчет грейда'!$I$19:$I$200)-18,""),ROW()-(ROW()-H$2))),"")} | I52: {=IFERROR(INDEX('Расчет грейда'!$I$19:$I$200,SMALL(IF('ТРС общая'!$B52='Расчет грейда'!$W$19:$W$200,ROW('Расчет грейда'!$I$19:$I$200)-18,""),ROW()-(ROW()-I$2))),"")} | J52: {=IFERROR(INDEX('Расчет грейда'!$I$19:$I$200,SMALL(IF('ТРС общая'!$B52='Расчет грейда'!$W$19:$W$200,ROW('Расчет грейда'!$I$19:$I$200)-18,""),ROW()-(ROW()-J$2))),"")} | K52: {=IFERROR(INDEX('Расчет грейда'!$I$19:$I$200,SMALL(IF('ТРС общая'!$B52='Расчет грейда'!$W$19:$W$200,ROW('Расчет грейда'!$I$19:$I$200)-18,""),ROW()-(ROW()-K$2))),"")} | ... AO52: {=IFERROR(INDEX('Расчет грейда'!$I$19:$I$200,SMALL(IF('ТРС общая'!$B52='Расчет грейда'!$W$19:$W$200,ROW('Расчет грейда'!$I$19:$I$200)-18,""),ROW()-(ROW()-AO$2))),"")}
... B61: 0 | C61: =COUNTIF('Расчет грейда'!$W:$W,'ТРС общая'!$B61) -> 0 | D61: {=IFERROR(INDEX('Расчет грейда'!$I$19:$I$200,SMALL(IF('ТРС общая'!$B61='Расчет грейда'!$W$19:$W$200,ROW('Расчет грейда'!$I$19:$I$200)-18,""),ROW()-(ROW()-D$2))),"")} -> 0 | E61: {=IFERROR(INDEX('Расчет грейда'!$I$19:$I$200,SMALL(IF('ТРС общая'!$B61='Расчет грейда'!$W$19:$W$200,ROW('Расчет грейда'!$I$19:$I$200)-18,""),ROW()-(ROW()-E$2))),"")} -> 0 | F61: {=IFERROR(INDEX('Расчет грейда'!$I$19:$I$200,SMALL(IF('ТРС общая'!$B61='Расчет грейда'!$W$19:$W$200,ROW('Расчет грейда'!$I$19:$I$200)-18,""),ROW()-(ROW()-F$2))),"")} -> 0 | G61: {=IFERROR(INDEX('Расчет грейда'!$I$19:$I$200,SMALL(IF('ТРС общая'!$B61='Расчет грейда'!$W$19:$W$200,ROW('Расчет грейда'!$I$19:$I$200)-18,""),ROW()-(ROW()-G$2))),"")} -> 0 | H61: {=IFERROR(INDEX('Расчет грейда'!$I$19:$I$200,SMALL(IF('ТРС общая'!$B61='Расчет грейда'!$W$19:$W$200,ROW('Расчет грейда'!$I$19:$I$200)-18,""),ROW()-(ROW()-H$2))),"")} -> 0 | I61: {=IFERROR(INDEX('Расчет грейда'!$I$19:$I$200,SMALL(IF('ТРС общая'!$B61='Расчет грейда'!$W$19:$W$200,ROW('Расчет грейда'!$I$19:$I$200)-18,""),ROW()-(ROW()-I$2))),"")} -> 0 | J61: {=IFERROR(INDEX('Расчет грейда'!$I$19:$I$200,SMALL(IF('ТРС общая'!$B61='Расчет грейда'!$W$19:$W$200,ROW('Расчет грейда'!$I$19:$I$200)-18,""),ROW()-(ROW()-J$2))),"")} -> 0 | K61: {=IFERROR(INDEX('Расчет грейда'!$I$19:$I$200,SMALL(IF('ТРС общая'!$B61='Расчет грейда'!$W$19:$W$200,ROW('Расчет грейда'!$I$19:$I$200)-18,""),ROW()-(ROW()-K$2))),"")} -> 0 | ... AO61: {=IFERROR(INDEX('Расчет грейда'!$I$19:$I$200,SMALL(IF('ТРС общая'!$B61='Расчет грейда'!$W$19:$W$200,ROW('Расчет грейда'!$I$19:$I$200)-18,""),ROW()-(ROW()-AO$2))),"")}

Sheet справочная информация
D3: Т. Ориентированные на задачи | E3: Т. Ориентированные на задачи | F3: Т. Ориентированные на задачи | G3: I. Ориентированные на конкретные процессы | H3: I. Ориентированные на конкретные процессы | I3: I. Ориентированные на конкретные процессы | J3: II. Однородные | K3: II. Однородные | L3: II. Однородные | M3: III. Разнородные | N3: III. Разнородные | O3: III. Разнородные | P3: IV. Всеохватывающие | Q3: IV. Всеохватывающие | R3: IV. Всеохватывающие | W3: Т. Ориентированные на задачи | X3: Т. Ориентированные на задачи | Y3: Т. Ориентированные на задачи | Z3: I. Ориентированные на конкретные процессы | AA3: I. Ориентированные на конкретные процессы | AB3: I. Ориентированные на конкретные процессы | AC3: II. Однородные | AD3: II. Однородные | AE3: II. Однородные | AF3: III. Разнородные | AG3: III. Разнородные | AH3: III. Разнородные | AI3: IV. Всеохватывающие | AJ3: IV. Всеохватывающие | AK3: IV. Всеохватывающие
D4: 1. Коммуникация | E4: 2. Обоснование и аргументация | F4: 3. Убеждение | G4: 1. Коммуникация | H4: 2. Обоснование и аргументация | I4: 3. Убеждение | J4: 1. Коммуникация | K4: 2. Обоснование и аргументация | L4: 3. Убеждение | M4: 1. Коммуникация | N4: 2. Обоснование и аргументация | O4: 3. Убеждение | P4: 1. Коммуникация | Q4: 2. Обоснование и аргументация | R4: 3. Убеждение | W4: 1. Коммуникация | X4: 2. Обоснование и аргументация | Y4: 3. Убеждение | Z4: 1. Коммуникация | AA4: 2. Обоснование и аргументация | AB4: 3. Убеждение | AC4: 1. Коммуникация | AD4: 2. Обоснование и аргументация | AE4: 3. Убеждение | AF4: 1. Коммуникация | AG4: 2. Обоснование и аргументация | AH4: 3. Убеждение | AI4: 1. Коммуникация | AJ4: 2. Обоснование и аргументация | AK4: 3. Убеждение
C5: Знания и умения | D5: =CONCATENATE(D3,D4) -> Т. Ориентированные на задачи1. Коммуникация | E5: =CONCATENATE(E3,E4) -> Т. Ориентированные на задачи2. Обоснование и аргументация | F5: =CONCATENATE(F3,F4) -> Т. Ориентированные на задачи3. Убеждение | G5: =CONCATENATE(G3,G4) -> I. Ориентированные на конкретные процессы1. Коммуникация | H5: =CONCATENATE(H3,H4) -> I. Ориентированные на конкретные процессы2. Обоснование и аргументация | I5: =CONCATENATE(I3,I4) -> I. Ориентированные на конкретные процессы3. Убеждение | J5: =CONCATENATE(J3,J4) -> II. Однородные1. Коммуникация | K5: =CONCATENATE(K3,K4) -> II. Однородные2. Обоснование и аргументация | ... R5: =CONCATENATE(R3,R4) -> IV. Всеохватывающие3. Убеждение | V5: Знания и умения | W5: =CONCATENATE(W3,W4) -> Т. Ориентированные на задачи1. Коммуникация | X5: =CONCATENATE(X3,X4) -> Т. Ориентированные на задачи2. Обоснование и аргументация | Y5: =CONCATENATE(Y3,Y4) -> Т. Ориентированные на задачи3. Убеждение | Z5: =CONCATENATE(Z3,Z4) -> I. Ориентированные на конкретные процессы1. Коммуникация | AA5: =CONCATENATE(AA3,AA4) -> I. Ориентированные на конкретные процессы2. Обоснование и аргументация | AB5: =CONCATENATE(AB3,AB4) -> I. Ориентированные на конкретные процессы3. Убеждение | AC5: =CONCATENATE(AC3,AC4) -> II. Однородные1. Коммуникация | AD5: =CONCATENATE(AD3,AD4) -> II. Однородные2. Обоснование и аргументация | ... AK5: =CONCATENATE(AK3,AK4) -> IV. Всеохватывающие3. Убеждение
A6: =CONCATENATE(C6,B6) -> А. Элементарные. Базовые.(-) | B6: (-) | C6: А. Элементарные. Базовые. | D6: 38 | E6: 43 | F6: 50 | G6: 50 | H6: 57 | I6: 66 | J6: 66 | K6: 76 | L6: 87 | M6: 87 | N6: 100 | O6: 115 | P6: 115 | Q6: 132 | R6: 152.09524 | T6: =CONCATENATE(V6,U6) -> А. Элементарные. Базовые.(-) | U6: (-) | V6: А. Элементарные. Базовые. | W6: Б | X6: Ж | Y6: С | Z6: Ж | AA6: С | AB6: С | AC6: С | AD6: С | AE6: С | AF6: С | AG6: С | AH6: С | AI6: С | AJ6: С | AK6: С
A7: =CONCATENATE(C7,B7) -> А. Элементарные. Базовые. | C7: А. Элементарные. Базовые. | D7: 43 | E7: 50 | F7: 57 | G7: 57 | H7: 66 | I7: 76 | J7: 76 | K7: 87 | L7: 100 | M7: 100 | N7: 115 | O7: 132 | P7: 132 | Q7: 152 | R7: 175 | T7: =CONCATENATE(V7,U7) -> А. Элементарные. Базовые. | V7: А. Элементарные. Базовые. | W7: Б | X7: Ж | Y7: С | Z7: Ж | AA7: С | AB7: С | AC7: С | AD7: С | AE7: С | AF7: С | AG7: С | AH7: С | AI7: С | AJ7: С | AK7: С
A8: =CONCATENATE(C8,B8) -> А. Элементарные. Базовые.(+) | B8: (+) | C8: А. Элементарные. Базовые. | D8: 50 | E8: 57 | F8: 66 | G8: 66 | H8: 76 | I8: 87 | J8: 87 | K8: 100 | L8: 115 | M8: 115 | N8: 132 | O8: 152 | P8: 152 | Q8: 175 | R8: 200 | T8: =CONCATENATE(V8,U8) -> А. Элементарные. Базовые.(+) | U8: (+) | V8: А. Элементарные. Базовые. | W8: Б | X8: Ж | Y8: С | Z8: Ж | AA8: С | AB8: С | AC8: С | AD8: С | AE8: С | AF8: С | AG8: С | AH8: С | AI8: С | AJ8: С | AK8: С
A9: =CONCATENATE(C9,B9) -> В. Начальные практические(-) | B9: (-) | C9: В. Начальные практические | D9: 50 | E9: 57 | F9: 66 | G9: 66 | H9: 76 | I9: 87 | J9: 87 | K9: 100 | L9: 115 | M9: 132 | N9: 152 | O9: 152 | P9: 152 | Q9: 175 | R9: 200 | T9: =CONCATENATE(V9,U9) -> В. Начальные практические(-) | U9: (-) | V9: В. Начальные практические | W9: Б | X9: Б | Y9: С | Z9: Б | AA9: Б | AB9: Ж | AC9: С | AD9: С | AE9: С | AF9: С | AG9: С | AH9: С | AI9: С | AJ9: С | AK9: С
A10: =CONCATENATE(C10,B10) -> В. Начальные практические | C10: В. Начальные практические | D10: 57 | E10: 66 | F10: 76 | G10: 76 | H10: 87 | I10: 100 | J10: 100 | K10: 115 | L10: 132 | M10: 132 | N10: 152 | O10: 175 | P10: 175 | Q10: 200 | R10: 230 | T10: =CONCATENATE(V10,U10) -> В. Начальные практические | V10: В. Начальные практические | W10: Б | X10: Б | Y10: С | Z10: Б | AA10: Б | AB10: Ж | AC10: С | AD10: С | AE10: С | AF10: С | AG10: С | AH10: С | AI10: С | AJ10: С | AK10: С
A11: =CONCATENATE(C11,B11) -> В. Начальные практические(+) | B11: (+) | C11: В. Начальные практические | D11: 66 | E11: 76 | F11: 87 | G11: 87 | H11: 100 | I11: 115 | J11: 115 | K11: 132 | L11: 152 | M11: 152 | N11: 175 | O11: 200 | P11: 200 | Q11: 230 | R11: 264 | T11: =CONCATENATE(V11,U11) -> В. Начальные практические(+) | U11: (+) | V11: В. Начальные практические | W11: Б | X11: Б | Y11: С | Z11: Б | AA11: Б | AB11: Ж | AC11: С | AD11: С | AE11: С | AF11: С | AG11: С | AH11: С | AI11: С | AJ11: С | AK11: С
A12: =CONCATENATE(C12,B12) -> С. Общие практические(-) | B12: (-) | C12: С. Общие практические | D12: 66 | E12: 76 | F12: 87 | G12: 87 | H12: 100 | I12: 115 | J12: 115 | K12: 132 | L12: 152 | M12: 175 | N12: 200 | O12: 200 | P12: 200 | Q12: 230 | R12: 264 | T12: =CONCATENATE(V12,U12) -> С. Общие практические(-) | U12: (-) | V12: С. Общие практические | W12: Б | X12: Б | Y12: С | Z12: Б | AA12: Б | AB12: Б | AC12: С | AD12: С | AE12: С | AF12: С | AG12: С | AH12: С | AI12: С | AJ12: С | AK12: С
A13: =CONCATENATE(C13,B13) -> С. Общие практические | C13: С. Общие практические | D13: 76 | E13: 87 | F13: 100 | G13: 100 | H13: 115 | I13: 132 | J13: 132 | K13: 152 | L13: 175 | M13: 175 | N13: 200 | O13: 230 | P13: 230 | Q13: 264 | R13: 304 | T13: =CONCATENATE(V13,U13) -> С. Общие практические | V13: С. Общие практические | W13: Б | X13: Б | Y13: С | Z13: Б | AA13: Б | AB13: Б | AC13: С | AD13: С | AE13: С | AF13: С | AG13: С | AH13: С | AI13: С | AJ13: С | AK13: С
A14: =CONCATENATE(C14,B14) -> С. Общие практические(+) | B14: (+) | C14: С. Общие практические | D14: 87 | E14: 100 | F14: 115 | G14: 115 | H14: 132 | I14: 152 | J14: 152 | K14: 175 | L14: 200 | M14: 200 | N14: 230 | O14: 264 | P14: 264 | Q14: 304 | R14: 350 | T14: =CONCATENATE(V14,U14) -> С. Общие практические(+) | U14: (+) | V14: С. Общие практические | W14: Б | X14: Б | Y14: С | Z14: Б | AA14: Б | AB14: Б | AC14: С | AD14: С | AE14: С | AF14: С | AG14: С | AH14: С | AI14: С | AJ14: С | AK14: С
A15: =CONCATENATE(C15,B15) -> D. Продвинутые практические(-) | B15: (-) | C15: D. Продвинутые практические | D15: 87 | E15: 100 | F15: 115 | G15: 115 | H15: 132 | I15: 152 | J15: 152 | K15: 175 | L15: 200 | M15: 230 | N15: 264 | O15: 264 | P15: 264 | Q15: 304 | R15: 350 | T15: =CONCATENATE(V15,U15) -> D. Продвинутые практические(-) | U15: (-) | V15: D. Продвинутые практические | W15: Ж | X15: С | Y15: С | Z15: Б | AA15: Б | AB15: Б | AC15: С | AD15: Ж | AE15: Ж | AF15: С | AG15: С | AH15: С | AI15: С | AJ15: С | AK15: С
A16: =CONCATENATE(C16,B16) -> D. Продвинутые практические | C16: D. Продвинутые практические | D16: 100 | E16: 115 | F16: 132 | G16: 132 | H16: 152 | I16: 175 | J16: 175 | K16: 200 | L16: 230 | M16: 230 | N16: 264 | O16: 304 | P16: 304 | Q16: 350 | R16: 400 | T16: =CONCATENATE(V16,U16) -> D. Продвинутые практические | V16: D. Продвинутые практические | W16: Ж | X16: С | Y16: С | Z16: Б | AA16: Б | AB16: Б | AC16: С | AD16: Ж | AE16: Ж | AF16: С | AG16: С | AH16: С | AI16: С | AJ16: С | AK16: С
A17: =CONCATENATE(C17,B17) -> D. Продвинутые практические(+) | B17: (+) | C17: D. Продвинутые практические | D17: 115 | E17: 132 | F17: 152 | G17: 152 | H17: 175 | I17: 200 | J17: 200 | K17: 230 | L17: 264 | M17: 264 | N17: 304 | O17: 350 | P17: 350 | Q17: 400 | R17: 460 | T17: =CONCATENATE(V17,U17) -> D. Продвинутые практические(+) | U17: (+) | V17: D. Продвинутые практические | W17: Ж | X17: С | Y17: С | Z17: Б | AA17: Б | AB17: Б | AC17: С | AD17: Ж | AE17: Ж | AF17: С | AG17: С | AH17: С | AI17: С | AJ17: С | AK17: С
A18: =CONCATENATE(C18,B18) -> E. Профессиональные(-) | B18: (-) | C18: E. Профессиональные | D18: 115 | E18: 132 | F18: 152 | G18: 152 | H18: 175 | I18: 200 | J18: 200 | K18: 230 | L18: 264 | M18: 264 | N18: 304 | O18: 350 | P18: 350 | Q18: 400 | R18: 460 | T18: =CONCATENATE(V18,U18) -> E. Профессиональные(-) | U18: (-) | V18: E. Профессиональные | W18: С | X18: С | Y18: С | Z18: Б | AA18: Б | AB18: Б | AC18: Ж | AD18: Б | AE18: Б | AF18: С | AG18: С | AH18: С | AI18: С | AJ18: С | AK18: С
A19: =CONCATENATE(C19,B19) -> E. Профессиональные | C19: E. Профессиональные | D19: 132 | E19: 152 | F19: 175 | G19: 175 | H19: 200 | I19: 230 | J19: 230 | K19: 264 | L19: 304 | M19: 304 | N19: 350 | O19: 400 | P19: 400 | Q19: 460 | R19: 528 | T19: =CONCATENATE(V19,U19) -> E. Профессиональные | V19: E. Профессиональные | W19: С | X19: С | Y19: С | Z19: Б | AA19: Б | AB19: Б | AC19: Ж | AD19: Б | AE19: Б | AF19: С | AG19: С | AH19: С | AI19: С | AJ19: С | AK19: С
A20: =CONCATENATE(C20,B20) -> E. Профессиональные(+) | B20: (+) | C20: E. Профессиональные | D20: 152 | E20: 175 | F20: 200 | G20: 200 | H20: 230 | I20: 264 | J20: 264 | K20: 304 | L20: 350 | M20: 350 | N20: 400 | O20: 460 | P20: 460 | Q20: 528 | R20: 608 | T20: =CONCATENATE(V20,U20) -> E. Профессиональные(+) | U20: (+) | V20: E. Профессиональные | W20: С | X20: С | Y20: С | Z20: Б | AA20: Б | AB20: Б | AC20: Ж | AD20: Б | AE20: Б | AF20: С | AG20: С | AH20: С | AI20: С | AJ20: С | AK20: С
A21: =CONCATENATE(C21,B21) -> F. Зрелые профессиональные(-) | B21: (-) | C21: F. Зрелые профессиональные | D21: 152 | E21: 175 | F21: 200 | G21: 200 | H21: 230 | I21: 264 | J21: 264 | K21: 304 | L21: 350 | M21: 350 | N21: 400 | O21: 460 | P21: 460 | Q21: 528 | R21: 608 | T21: =CONCATENATE(V21,U21) -> F. Зрелые профессиональные(-) | U21: (-) | V21: F. Зрелые профессиональные | W21: С | X21: С | Y21: С | Z21: Б | AA21: Б | AB21: Б | AC21: Ж | AD21: Б | AE21: Б | AF21: С | AG21: Ж | AH21: Б | AI21: С | AJ21: С | AK21: Ж
A22: =CONCATENATE(C22,B22) -> F. Зрелые профессиональные | C22: F. Зрелые профессиональные | D22: 175 | E22: 200 | F22: 230 | G22: 230 | H22: 264 | I22: 304 | J22: 304 | K22: 350 | L22: 400 | M22: 400 | N22: 460 | O22: 528 | P22: 528 | Q22: 608 | R22: 700 | T22: =CONCATENATE(V22,U22) -> F. Зрелые профессиональные | V22: F. Зрелые профессиональные | W22: С | X22: С | Y22: С | Z22: Б | AA22: Б | AB22: Б | AC22: Ж | AD22: Б | AE22: Б | AF22: С | AG22: Ж | AH22: Б | AI22: С | AJ22: С | AK22: Ж
A23: =CONCATENATE(C23,B23) -> F. Зрелые профессиональные(+) | B23: (+) | C23: F. Зрелые профессиональные | D23: 200 | E23: 230 | F23: 264 | G23: 264 | H23: 304 | I23: 350 | J23: 350 | K23: 400 | L23: 460 | M23: 460 | N23: 528 | O23: 608 | P23: 608 | Q23: 700 | R23: 800 | T23: =CONCATENATE(V23,U23) -> F. Зрелые профессиональные(+) | U23: (+) | V23: F. Зрелые профессиональные | W23: С | X23: С | Y23: С | Z23: Б | AA23: Б | AB23: Б | AC23: Ж | AD23: Б | AE23: Б | AF23: С | AG23: Ж | AH23: Б | AI23: С | AJ23: С | AK23: Ж
A24: =CONCATENATE(C24,B24) -> G. Всесторонние(-) | B24: (-) | C24: G. Всесторонние | D24: 200 | E24: 230 | F24: 264 | G24: 264 | H24: 304 | I24: 350 | J24: 350 | K24: 400 | L24: 460 | M24: 460 | N24: 528 | O24: 608 | P24: 608 | Q24: 700 | R24: 800 | T24: =CONCATENATE(V24,U24) -> G. Всесторонние(-) | U24: (-) | V24: G. Всесторонние | W24: С | X24: С | Y24: С | Z24: Б | AA24: Б | AB24: Б | AC24: Ж | AD24: Б | AE24: Б | AF24: С | AG24: Ж | AH24: Б | AI24: С | AJ24: С | AK24: Б
A25: =CONCATENATE(C25,B25) -> G. Всесторонние | C25: G. Всесторонние | D25: 230 | E25: 264 | F25: 304 | G25: 304 | H25: 350 | I25: 400 | J25: 400 | K25: 460 | L25: 528 | M25: =L25 -> 528 | N25: 608 | O25: 700 | P25: 700 | Q25: 800 | R25: 920 | T25: =CONCATENATE(V25,U25) -> G. Всесторонние | V25: G. Всесторонние | W25: С | X25: С | Y25: С | Z25: Б | AA25: Б | AB25: Б | AC25: Ж | AD25: Б | AE25: Б | AF25: С | AG25: Ж | AH25: Б | AI25: С | AJ25: С | AK25: Б
A26: =CONCATENATE(C26,B26) -> G. Всесторонние(+) | B26: (+) | C26: G. Всесторонние | D26: 264 | E26: 304 | F26: 350 | G26: 350 | H26: 400 | I26: 460 | J26: =J27 -> 460 | K26: 528 | L26: 608 | M26: =L26 -> 608 | N26: =N27 -> 700 | O26: =O27 -> 800 | P26: 800 | Q26: 920 | R26: 1056 | T26: =CONCATENATE(V26,U26) -> G. Всесторонние(+) | U26: (+) | V26: G. Всесторонние | W26: С | X26: С | Y26: С | Z26: Б | AA26: Б | AB26: Б | AC26: =AC27 -> Ж | AD26: Б | AE26: Б | AF26: С | AG26: Ж | AH26: Б | AI26: С | AJ26: С | AK26: Б
A27: =CONCATENATE(C27,B27) -> H. Уникальные(-) | B27: (-) | C27: H. Уникальные | D27: 264 | E27: 304 | F27: 350 | G27: 350 | H27: 400 | I27: =I26 -> 460 | J27: 460 | K27: =K26 -> 528 | L27: =L26 -> 608 | M27: =L27 -> 608 | N27: 700 | O27: 800 | P27: 800 | Q27: 920 | R27: 1056 | T27: =CONCATENATE(V27,U27) -> H. Уникальные(-) | U27: (-) | V27: H. Уникальные | W27: С | X27: С | Y27: С | Z27: Б | AA27: Б | AB27: Ж | AC27: Ж | AD27: Б | AE27: Б | AF27: С | AG27: Ж | AH27: Б | AI27: С | AJ27: С | AK27: С
A28: =CONCATENATE(C28,B28) -> H. Уникальные | C28: H. Уникальные | D28: 304 | E28: 350 | F28: 400 | G28: 400 | H28: 460 | I28: 528 | J28: =I28 -> 528 | K28: =J29 -> 608 | L28: =K29 -> 700 | M28: 700 | N28: 800 | O28: 920 | P28: 920 | Q28: 1056 | R28: 1216 | T28: =CONCATENATE(V28,U28) -> H. Уникальные | V28: H. Уникальные | W28: С | X28: С | Y28: С | Z28: Б | AA28: Б | AB28: Ж | AC28: =AB28 -> Ж | AD28: Б | AE28: Б | AF28: С | AG28: Ж | AH28: Б | AI28: С | AJ28: С | AK28: С
A29: =CONCATENATE(C29,B29) -> H. Уникальные(+) | B29: (+) | C29: H. Уникальные | D29: 350 | E29: 400 | F29: 460 | G29: 460 | H29: 528 | I29: 608 | J29: =I29 -> 608 | K29: 700 | L29: 800 | M29: =L29 -> 800 | N29: 920 | O29: 1056 | P29: 1056 | Q29: 1216 | R29: 1400 | T29: =CONCATENATE(V29,U29) -> H. Уникальные(+) | U29: (+) | V29: H. Уникальные | W29: С | X29: С | Y29: С | Z29: Б | AA29: Б | AB29: Ж | AC29: =AB29 -> Ж | AD29: Б | AE29: Б | AF29: С | AG29: Ж | AH29: Б | AI29: С | AJ29: С | AK29: С
A30: =CONCATENATE(C30,B30)
A31: =CONCATENATE(C31,B31)
A32: =CONCATENATE(C32,B32)
A33: =CONCATENATE(C33,B33)
A34: =CONCATENATE(C34,B34)
A35: =CONCATENATE(C35,B35)
A36: =CONCATENATE(C36,B36) -> Решение вопросов | C36: Решение вопросов | D36: 1. Повторяющиеся однотипные вопросы | E36: 2. Подобные | F36: 3. Изменчивые вопросы | G36: 4. Нестандартные вопросы | H36: 5. Неизученные вопросы | V36: =W36=T25 -> TRUE | W36: G. Всесторонние
A37: =CONCATENATE(C37,B37) -> A.Строго "по шаблону" | C37: A.Строго "по шаблону" | D37: 0.1 | E37: 0.14 | F37: 0.19 | G37: 0.25 | H37: 0.33
A38: =CONCATENATE(C38,B38) -> A.Строго "по шаблону"(+) | B38: (+) | C38: A.Строго "по шаблону" | D38: 0.12 | E38: 0.16 | F38: 0.22 | G38: 0.29 | H38: 0.38
A39: =CONCATENATE(C39,B39) -> В. "По шаблону" | C39: В. "По шаблону" | D39: 0.12 | E39: 0.16 | F39: 0.22 | G39: 0.29 | H39: 0.38
A40: =CONCATENATE(C40,B40) -> В. "По шаблону"(+) | B40: (+) | C40: В. "По шаблону" | D40: 0.14 | E40: 0.19 | F40: 0.25 | G40: 0.33 | H40: 0.43
A41: =CONCATENATE(C41,B41) -> С. Процедурная | C41: С. Процедурная | D41: 0.14 | E41: 0.19 | F41: 0.25 | G41: 0.33 | H41: 0.43
A42: =CONCATENATE(C42,B42) -> С. Процедурная(+) | B42: (+) | C42: С. Процедурная | D42: 0.16 | E42: 0.22 | F42: 0.29 | G42: 0.38 | H42: 0.5
A43: =CONCATENATE(C43,B43) -> D. Нормативная | C43: D. Нормативная | D43: 0.16 | E43: 0.22 | F43: 0.29 | G43: 0.38 | H43: 0.5
A44: =CONCATENATE(C44,B44) -> D. Нормативная(+) | B44: (+) | C44: D. Нормативная | D44: 0.19 | E44: 0.25 | F44: 0.33 | G44: 0.43 | H44: 0.57
A45: =CONCATENATE(C45,B45) -> E. Ясно определенная | C45: E. Ясно определенная | D45: 0.19 | E45: 0.25 | F45: 0.33 | G45: 0.43 | H45: 0.57
A46: =CONCATENATE(C46,B46) -> E. Ясно определенная(+) | B46: (+) | C46: E. Ясно определенная | D46: 0.22 | E46: 0.29 | F46: 0.38 | G46: 0.5 | H46: 0.66
A47: =CONCATENATE(C47,B47) -> F. Широко определенная | C47: F. Широко определенная | D47: 0.22 | E47: 0.29 | F47: 0.38 | G47: 0.5 | H47: 0.66
A48: =CONCATENATE(C48,B48) -> F. Широко определенная(+) | B48: (+) | C48: F. Широко определенная | D48: 0.25 | E48: 0.33 | F48: 0.43 | G48: 0.57 | H48: 0.76
A49: =CONCATENATE(C49,B49) -> G. В целом определенная | C49: G. В целом определенная | D49: 0.25 | E49: 0.33 | F49: 0.43 | G49: 0.57 | H49: 0.76
A50: =CONCATENATE(C50,B50) -> G. В целом определенная (+) | B50: (+) | C50: G. В целом определенная | D50: 0.29 | E50: 0.38 | F50: 0.5 | G50: 0.66 | H50: 0.87
A51: =CONCATENATE(C51,B51) -> H. Абстрактно определенная | C51: H. Абстрактно определенная | D51: 0.29 | E51: 0.38 | F51: 0.5 | G51: 0.66 | H51: 0.87
A52: =CONCATENATE(C52,B52) -> H. Абстрактно определенная(+) | B52: (+) | C52: H. Абстрактно определенная | D52: 0.33 | E52: 0.43 | F52: 0.57 | G52: 0.76 | H52: 0.87
C55: Решение вопросов | D55: 1. Повторяющиеся однотипные вопросы | E55: 2. Подобные | F55: 3. Изменчивые вопросы | G55: 4. Нестандартные вопросы | H55: 5. Неизученные вопросы
C56: A.Строго "по шаблону" | D56: Работа в рамках строгих инструкций | E56: Рутинная работа с небольшим возможными отклонениями от нормы | F56: Оператор процесса | G56: Эксперт по процессу | H56: Совершенстовавание процедур
C57: В. "По шаблону" | D57: Возможность выбрать последовательность действий | E57: Возможность выбрать решения, основываясь на опыте или регламентах | F57: Специалист по процессу | G57: Супервайзинг | H57: Операционная реализация
C58: С. Процедурная | D58: Рутинная работа с небольшим возможными отклонениями от нормы | E58: Оператор процесса | F58: Эксперт по процессу | G58: Совершенстовавание процедур | H58: Тактическое внедрение
C59: D. Нормативная | D59: Возможность выбрать решения, основываясь на опыте или регламентах | E59: Специалист по процессу | F59: Супервайзинг | G59: Операционная реализация | H59: Реализация стратегии
C60: E. Ясно определенная | D60: Оператор процесса | E60: Эксперт по процессу | F60: Совершенстовавание процедур | G60: Тактическое внедрение | H60: Согласование стратегии
C61: F. Широко определенная | D61: Специалист по процессу | E61: Супервайзинг | F61: Операционная реализация | G61: Реализация стратегии | H61: Президент или исполнительный директор. Опре
C62: G. В целом определенная | D62: Эксперт по процессу | E62: Совершенстовавание процедур | F62: Тактическое внедрение | G62: Согласование стратегии | H62: Президент или исполнительный директор. Опре
C63: H. Абстрактно определенная | D63: Супервайзинг | E63: Операционная реализация | F63: Реализация стратегии | G63: Президент или исполнительный директор. Опре | H63: Президент или исполнительный директор. Опре
C67: Решение вопросов | D67: 1. Повторяющиеся однотипные вопросы | E67: 2. Подобные | F67: 3. Изменчивые вопросы | G67: 4. Нестандартные вопросы | H67: 5. Неизученные вопросы
A68: =CONCATENATE(C68,B68) -> A.Строго "по шаблону" | C68: A.Строго "по шаблону" | D68: Б | E68: Ж | F68: С | G68: С | H68: С
A69: =CONCATENATE(C69,B69) -> A.Строго "по шаблону"(+) | B69: (+) | C69: A.Строго "по шаблону" | D69: Б | E69: С | F69: С | G69: С | H69: С
A70: =CONCATENATE(C70,B70) -> В. "По шаблону" | C70: В. "По шаблону" | D70: Ж | E70: Б | F70: С | G70: С | H70: С
A71: =CONCATENATE(C71,B71) -> В. "По шаблону"(+) | B71: (+) | C71: В. "По шаблону" | D71: Б | E71: Б | F71: С | G71: С | H71: С
A72: =CONCATENATE(C72,B72) -> С. Процедурная | C72: С. Процедурная | D72: С | E72: Б | F72: Б | G72: С | H72: С
A73: =CONCATENATE(C73,B73) -> С. Процедурная(+) | B73: (+) | C73: С. Процедурная | D73: С | E73: Б | F73: Б | G73: С | H73: С
A74: =CONCATENATE(C74,B74) -> D. Нормативная | C74: D. Нормативная | D74: С | E74: С | F74: Б | G74: Б | H74: С
A75: =CONCATENATE(C75,B75) -> D. Нормативная(+) | B75: (+) | C75: D. Нормативная | D75: С | E75: Ж | F75: Б | G75: Ж | H75: С
A76: =CONCATENATE(C76,B76) -> E. Ясно определенная | C76: E. Ясно определенная | D76: С | E76: С | F76: Б | G76: Б | H76: Ж
A77: =CONCATENATE(C77,B77) -> E. Ясно определенная(+) | B77: (+) | C77: E. Ясно определенная | D77: С | E77: С | F77: Б | G77: Б | H77: Ж
A78: =CONCATENATE(C78,B78) -> F. Широко определенная | C78: F. Широко определенная | D78: С | E78: С | F78: С | G78: Б | H78: С
A79: =CONCATENATE(C79,B79) -> F. Широко определенная(+) | B79: (+) | C79: F. Широко определенная | D79: С | E79: С | F79: Ж | G79: Б | H79: С
A80: =CONCATENATE(C80,B80) -> G. В целом определенная | C80: G. В целом определенная | D80: С | E80: С | F80: С | G80: Б | H80: С
A81: =CONCATENATE(C81,B81) -> G. В целом определенная (+) | B81: (+) | C81: G. В целом определенная | D81: С | E81: С | F81: С | G81: Б | H81: С
A82: =CONCATENATE(C82,B82) -> H. Абстрактно определенная | C82: H. Абстрактно определенная | D82: С | E82: С | F82: С | G82: Ж | H82: Б
A83: =CONCATENATE(C83,B83) -> H. Абстрактно определенная(+) | B83: (+) | C83: H. Абстрактно определенная | D83: С | E83: С | F83: С | G83: Ж | H83: Б
D105: Решение вопросов
D107: 38 | E107: 43 | F107: 50 | G107: 57 | H107: 66 | I107: 76 | J107: 87 | K107: 100 | L107: 115 | M107: 132 | N107: 152 | O107: 175 | P107: 200 | Q107: 230 | R107: 264 | S107: 304 | T107: 350 | U107: 400 | V107: 460 | W107: 528 | X107: 608 | Y107: 700 | Z107: 800 | AA107: 920 | AB107: 1056 | AC107: 1216 | AD107: 1400
C108: 0.87 | D108: 33 | E108: 38 | F108: 43 | G108: 50 | H108: 57 | I108: 66 | J108: 76 | K108: 87 | L108: 100 | M108: 115 | N108: 132 | O108: 152 | P108: 175 | Q108: 200 | R108: 230 | S108: 264 | T108: 304 | U108: 350 | V108: 400 | W108: 460 | X108: 528 | Y108: 608 | Z108: 700 | AA108: 800 | AB108: 920 | AC108: 1056 | AD108: 1216
C109: 0.76 | D109: 29 | E109: 33 | F109: 38 | G109: 43 | H109: 50 | I109: 57 | J109: 66 | K109: 76 | L109: 87 | M109: 100 | N109: 115 | O109: 132 | P109: 152 | Q109: 175 | R109: 200 | S109: 230 | T109: 264 | U109: 304 | V109: 350 | W109: 400 | X109: 460 | Y109: 528 | Z109: 608 | AA109: 700 | AB109: 800 | AC109: 920 | AD109: 1056
C110: 0.66 | D110: 25 | E110: 29 | F110: 33 | G110: 38 | H110: 43 | I110: 50 | J110: 57 | K110: 66 | L110: 76 | M110: 87 | N110: 100 | O110: 115 | P110: 132 | Q110: 152 | R110: 175 | S110: 200 | T110: 230 | U110: 264 | V110: 304 | W110: 350 | X110: 400 | Y110: 460 | Z110: 528 | AA110: 608 | AB110: 700 | AC110: 800 | AD110: 920
C111: 0.57 | D111: 22 | E111: 25 | F111: 29 | G111: 33 | H111: 38 | I111: 43 | J111: 50 | K111: 57 | L111: 66 | M111: 76 | N111: 87 | O111: 100 | P111: 115 | Q111: 132 | R111: 152 | S111: 175 | T111: 200 | U111: 230 | V111: 264 | W111: 304 | X111: 350 | Y111: 400 | Z111: 460 | AA111: 528 | AB111: 608 | AC111: 700 | AD111: 800
C112: 0.5 | D112: 19 | E112: 22 | F112: 25 | G112: 29 | H112: 33 | I112: 38 | J112: 43 | K112: 50 | L112: 57 | M112: 66 | N112: 76 | O112: 87 | P112: 100 | Q112: 115 | R112: 132 | S112: 152 | T112: 175 | U112: 200 | V112: 230 | W112: 264 | X112: 304 | Y112: 350 | Z112: 400 | AA112: 460 | AB112: 528 | AC112: 608 | AD112: 700
C113: 0.43 | D113: 16 | E113: 19 | F113: 22 | G113: 25 | H113: 29 | I113: 33 | J113: 38 | K113: 43 | L113: 50 | M113: 57 | N113: 66 | O113: 76 | P113: 87 | Q113: 100 | R113: 115 | S113: 132 | T113: 152 | U113: 175 | V113: 200 | W113: 230 | X113: 264 | Y113: 304 | Z113: 350 | AA113: 400 | AB113: 460 | AC113: 528 | AD113: 608
C114: 0.38 | D114: 14 | E114: 16 | F114: 19 | G114: 22 | H114: 25 | I114: 29 | J114: 33 | K114: 38 | L114: 43 | M114: 50 | N114: 57 | O114: 66 | P114: 76 | Q114: 87 | R114: 100 | S114: 115 | T114: 132 | U114: 152 | V114: 175 | W114: 200 | X114: 230 | Y114: 264 | Z114: 304 | AA114: 350 | AB114: 400 | AC114: 460 | AD114: 528
C115: 0.33 | D115: 12 | E115: 14 | F115: 16 | G115: 19 | H115: 22 | I115: 25 | J115: 29 | K115: 33 | L115: 38 | M115: 43 | N115: 50 | O115: 57 | P115: 66 | Q115: 76 | R115: 87 | S115: 100 | T115: 115 | U115: 132 | V115: 152 | W115: 175 | X115: 200 | Y115: 230 | Z115: 264 | AA115: 304 | AB115: 350 | AC115: 400 | AD115: 460
C116: 0.29 | D116: 10 | E116: 12 | F116: 14 | G116: 16 | H116: 19 | I116: 22 | J116: 25 | K116: 29 | L116: 33 | M116: 38 | N116: 43 | O116: 50 | P116: 57 | Q116: 66 | R116: 76 | S116: 87 | T116: 100 | U116: 115 | V116: 132 | W116: 152 | X116: 175 | Y116: 200 | Z116: 230 | AA116: 264 | AB116: 304 | AC116: 350 | AD116: 400
C117: 0.25 | D117: 9 | E117: 10 | F117: 12 | G117: 14 | H117: 16 | I117: 19 | J117: 22 | K117: 25 | L117: 29 | M117: 33 | N117: 38 | O117: 43 | P117: 50 | Q117: 57 | R117: 66 | S117: 76 | T117: 87 | U117: 100 | V117: 115 | W117: 132 | X117: 152 | Y117: 175 | Z117: 200 | AA117: 230 | AB117: 264 | AC117: 304 | AD117: 350
C118: 0.22 | D118: 8 | E118: 9 | F118: 10 | G118: 12 | H118: 14 | I118: 16 | J118: 19 | K118: 22 | L118: 25 | M118: 29 | N118: 33 | O118: 38 | P118: 43 | Q118: 50 | R118: 57 | S118: 66 | T118: 76 | U118: 87 | V118: 100 | W118: 115 | X118: 132 | Y118: 152 | Z118: 175 | AA118: 200 | AB118: 230 | AC118: 264 | AD118: 304
C119: 0.19 | D119: 7 | E119: 8 | F119: 9 | G119: 10 | H119: 12 | I119: 14 | J119: 16 | K119: 19 | L119: 22 | M119: 25 | N119: 29 | O119: 33 | P119: 38 | Q119: 43 | R119: 50 | S119: 57 | T119: 66 | U119: 76 | V119: 87 | W119: 100 | X119: 115 | Y119: 132 | Z119: 152 | AA119: 175 | AB119: 200 | AC119: 230 | AD119: 264
... C123: 0.1 | D123: 4 | E123: 4 | F123: 5 | G123: 6 | H123: 7 | I123: 8 | J123: 9 | K123: 10 | L123: 12 | M123: 14 | N123: 16 | O123: 19 | P123: 22 | Q123: 25 | R123: 29 | S123: 33 | T123: 38 | U123: 43 | V123: 50 | W123: 57 | X123: 66 | Y123: 76 | Z123: 87 | AA123: 100 | AB123: 115 | AC123: 132 | AD123: 152
D128: Решение вопросов
D129: 38 | E129: 43 | F129: 50 | G129: 57 | H129: 66 | I129: 76 | J129: 87 | K129: 100 | L129: 115 | M129: 132 | N129: 152 | O129: 175 | P129: 200 | Q129: 230 | R129: 264 | S129: 304 | T129: 350 | U129: 400 | V129: 460 | W129: 528 | X129: 608 | Y129: 700 | Z129: 800 | AA129: 920 | AB129: 1056 | AC129: 1216 | AD129: 1400
C130: 0.87 | D130: С | E130: С | F130: С | G130: С | H130: С | I130: С | J130: С | K130: С | L130: С | M130: С | N130: С | O130: С | P130: С | Q130: С | R130: С | S130: С | T130: С | U130: С | V130: С | W130: С | X130: С | Y130: С | Z130: С | AA130: С | AB130: С | AC130: Ж | AD130: Ж
C131: 0.76 | D131: С | E131: С | F131: С | G131: С | H131: С | I131: С | J131: С | K131: С | L131: С | M131: С | N131: С | O131: С | P131: С | Q131: С | R131: С | S131: С | T131: С | U131: С | V131: С | W131: С | X131: С | Y131: Ж | Z131: Ж | AA131: Б | AB131: Б | AC131: Б | AD131: Б
C132: 0.66 | D132: С | E132: С | F132: С | G132: С | H132: С | I132: С | J132: С | K132: С | L132: С | M132: С | N132: С | O132: С | P132: С | Q132: С | R132: С | S132: С | T132: С | U132: С | V132: С | W132: С | X132: Ж | Y132: Б | Z132: Б | AA132: Б | AB132: Б | AC132: Б | AD132: Б
C133: 0.57 | D133: С | E133: С | F133: С | G133: С | H133: С | I133: С | J133: С | K133: С | L133: С | M133: С | N133: С | O133: С | P133: С | Q133: С | R133: С | S133: С | T133: С | U133: Ж | V133: Б | W133: Б | X133: Б | Y133: Б | Z133: Б | AA133: Б | AB133: Б | AC133: Ж | AD133: Ж
C134: 0.5 | D134: С | E134: С | F134: С | G134: С | H134: С | I134: С | J134: С | K134: С | L134: С | M134: С | N134: С | O134: С | P134: С | Q134: С | R134: С | S134: Ж | T134: Б | U134: Б | V134: Б | W134: Б | X134: Б | Y134: Ж | Z134: С | AA134: С | AB134: С | AC134: С | AD134: С
C135: 0.43 | D135: С | E135: С | F135: С | G135: С | H135: С | I135: С | J135: С | K135: С | L135: С | M135: С | N135: С | O135: С | P135: С | Q135: Ж | R135: Б | S135: Б | T135: Б | U135: Б | V135: Б | W135: Ж | X135: С | Y135: С | Z135: С | AA135: С | AB135: С | AC135: С | AD135: С
C136: 0.38 | D136: С | E136: С | F136: С | G136: С | H136: С | I136: С | J136: С | K136: С | L136: С | M136: С | N136: С | O136: С | P136: Ж | Q136: Б | R136: Б | S136: Б | T136: Б | U136: Ж | V136: С | W136: С | X136: С | Y136: С | Z136: С | AA136: С | AB136: С | AC136: С | AD136: С
...
